CompArch/hw5/hw5a/llwalk.v
/*          OPCODE SRC  DST  IMMDATA */
myROM[0]  = {movi, RXX, Rg0, 4'b0000};
myROM[1]  = {movi, RXX, Rg1, 4'b0000};
myROM[2]  = {lw,   Rg1, Rg3, 4'b0000};
myROM[3]  = {add,  Rg3, Rg0, 4'b0000};
myROM[4]  = {addi, RXX, Rg1, 4'b0001};
myROM[5]  = {lw,   Rg1, Rg1, 4'b0000};
myROM[6]  = {cmpi, RXX, Rg1, 4'b1111};
myROM[7]  = {jnz,  RXX, RXX, 4'b1011};
myROM[8]  = {jmp,  RXX, RXX, 4'b0000};
myROM[9]  = {jmp,  RXX, RXX, 4'b0000};
myROM[10] = {jmp,  RXX, RXX, 4'b0000};
myROM[11] = {jmp,  RXX, RXX, 4'b0000};
myROM[12] = {jmp,  RXX, RXX, 4'b0000};
myROM[13] = {jmp,  RXX, RXX, 4'b0000};
myROM[14] = {jmp,  RXX, RXX, 4'b0000};
myROM[15] = {jmp,  RXX, RXX, 4'b0000};

CompArch/hw5/hw5a/E15Mem.v
module E15Mem(input clk, 
              input wire write_enable,
              input wire [3:0] address,
              input wire [3:0] valueIn,
              output wire [3:0] valueOut 
                  );
   reg [3:0] memory [15:0];

   assign valueOut = memory[address];
   
   always @(posedge clk)
     if (write_enable)
      begin
        memory[address] <= valueIn;
      end

endmodule

CompArch/hw5/hw5a/E15Process_mem.v
`include "E15Mem.v"

module E15Process(input clk,
                  output reg [3:0] pc,             // Program Counter
                  output reg [3:0] opCode,         // op code
                  output reg [1:0] src, dst,       // src and dst register
                  output reg [3:0] immData,        // "Immediate" data
                  output reg [3:0] r0, r1, r2, r3, // Registers
                  output tri [3:0] mBus, dstBus    // Buses
                  );

   parameter fetch=2'd0, decode=2'd1, exec=2'd2, store=2'd3;

   parameter Rg0 = 2'b00, Rg1 = 2'b01, Rg2 = 2'b10, Rg3 = 2'b11,
             RXX = 2'b00;

   parameter
     jmp  = 4'b0000, jz   = 4'b0010,  jnz = 4'b0011,
     movi = 4'b1001, mov  = 4'b1000,
     addi = 4'b1011, add  = 4'b1010,
     subi = 4'b1101, sub  = 4'b1100,
     cmpi = 4'b1111, cmp  = 4'b1110,
     lw = 4'b0100, sw = 4'b0101, swi = 4'b0111;


   parameter   hiZ = 4'bz;

   parameter   bEn_R0 = 3'd0, bEn_R1 = 3'd1,
     bEn_R2 = 3'd2, bEn_R3 = 3'd3,
     bEn_ALU = 3'd4, bEn_Imm = 3'd5;

   reg  [3:0] pcIncr; // Program Counter Increment
   wire [3:0] pcRes;  // Output of pc ALU
   wire       pcz;    // Unused - zero flag for pc ALU

   reg [1:0]  myState;      // State (phase of excution)
   reg [11:0] myROM [15:0]; // ROM (holds program)
   reg [3:0]  mbEn, dbEn;   // Used to determine which tri-state buffers are
                            // enabled for master bus and destination bus.

   reg       mmuControl; // read or write the mmu
   wire [3:0] mmuValueOut; // output value from mmu
   reg        addNotSub; // Determines if ALU adds or subtracts
   reg [3:0]  aluOut;    // Register to hold output of main ALU
   reg        zFlag;     // Zero flag
   wire [3:0] resVal;    // Output (combinational) of ALU
   wire       zVal;      // Output (combinational) of ALU zero flag

   initial
     begin

        `include "llwalk.v"

        pc = 4'b0000;
        myState = fetch;

     end

   always @(posedge clk)
     case(myState)
       fetch:
         begin
            {opCode, src, dst, immData} = myROM[pc];
            mmuControl <= 0;
            myState <= decode;
         end

       decode:
         begin
            case(opCode)
              movi, addi, subi, cmpi, swi:
                begin
                   mbEn <= bEn_Imm;
                end
              mov, add, sub, cmp, lw, sw:
                case(src)
                  Rg0: mbEn <= bEn_R0;
                  Rg1: mbEn <= bEn_R1;
                  Rg2: mbEn <= bEn_R2;
                  Rg3: mbEn <= bEn_R3;
                endcase
            endcase

            case(dst)
              Rg0: dbEn <= bEn_R0;
              Rg1: dbEn <= bEn_R1;
              Rg2: dbEn <= bEn_R2;
              Rg3: dbEn <= bEn_R3;
            endcase

            mmuControl <= ((opCode == sw) | (opCode == swi));
            addNotSub <= ((opCode == add) | (opCode == addi));
            myState <= exec;
         end

       exec:
         begin
            case(opCode)
              lw:
                begin
                   pcIncr <= 4'd1;
                   mbEn <= bEn_ALU;
                   aluOut <= mmuValueOut;
                end
              addi, add, subi, sub, cmpi, cmp:
                begin
                   pcIncr <= 4'd1;
                   mbEn <= bEn_ALU;
                   aluOut <= resVal;
                   zFlag <= zVal;
                end
              jmp: pcIncr <= immData;
              jz:  pcIncr <= zFlag ? immData : 4'd1;
              jnz: pcIncr <= zFlag ? 4'd1 : immData;
              default: pcIncr <= 4'd1;
            endcase
            myState <= store;
         end

       store:
         begin
            case(opCode)
              movi, mov, add, addi, sub, subi, lw:
                case(dst)
                  Rg0: r0 <= mBus;
                  Rg1: r1 <= mBus;
                  Rg2: r2 <= mBus;
                  Rg3: r3 <= mBus;
                endcase
            endcase
            pc <= pcRes;
            mmuControl <= 0;
            myState <= fetch;
         end

     endcase

   assign mBus = (mbEn==bEn_R0)  ? r0      : hiZ;
   assign mBus = (mbEn==bEn_R1)  ? r1      : hiZ;
   assign mBus = (mbEn==bEn_R2)  ? r2      : hiZ;
   assign mBus = (mbEn==bEn_R3)  ? r3      : hiZ;
   assign mBus = (mbEn==bEn_Imm) ? immData : hiZ;
   assign mBus = (mbEn==bEn_ALU) ? aluOut  : hiZ;

   assign dstBus = (dbEn==bEn_R0)  ? r0 : hiZ;
   assign dstBus = (dbEn==bEn_R1)  ? r1 : hiZ;
   assign dstBus = (dbEn==bEn_R2)  ? r2 : hiZ;
   assign dstBus = (dbEn==bEn_R3)  ? r3 : hiZ;

   simpleALU dataALU(addNotSub, mBus, dstBus, zVal, resVal);
   simpleALU pcALU(1'b1, pc, pcIncr, pcz, pcRes);

   E15Mem MMU(clk, mmuControl, mBus, dstBus, mmuValueOut);

endmodule


module simpleALU(
    input addNotSub,
    input [3:0] src, dst,
    output zFlag,
    output [3:0] res);
    assign res = addNotSub ? dst + src : dst - src;
    assign zFlag = !(res);

endmodule

CompArch/hw5/hw5a/E15Process_mem_tb.v
`default_nettype none
`timescale 1ns/100ps
`include "E15Process_mem.v"

module E15Process_TB;

   reg clk = 0;

   wire [3:0] pc;
   wire [3:0] opCode;
   wire [1:0] src, dst;
   wire [3:0] immData;
   wire [3:0] r0, r1, r2, r3;
   tri [3:0]  mBus, dstBus;

   E15Process proc(clk, pc, opCode, src, dst, immData, 
                   r0, r1, r2, r3, mBus, dstBus);

   always #1
     clk = ~clk;

   integer i;
   initial begin
      // the linked list, starting at address 0
      proc.MMU.memory[0] = 0;
      proc.MMU.memory[1] = 4;
      proc.MMU.memory[2] = 15;
      proc.MMU.memory[3] = 3;
      proc.MMU.memory[4] = 1;
      proc.MMU.memory[5] = 14;
      proc.MMU.memory[6] = 6;
      proc.MMU.memory[7] = 15;
      proc.MMU.memory[8] = 0;
      proc.MMU.memory[9] = 0;
      proc.MMU.memory[10] = 2;
      proc.MMU.memory[11] = 6;
      proc.MMU.memory[12] = 4;
      proc.MMU.memory[13] = 14;
      proc.MMU.memory[14] = 0;
      proc.MMU.memory[15] = 10;
      $dumpfile("E15Process_tb.vcd");
      $dumpvars(0, E15Process_TB);
      #1000

      $display("Final state of register file:\n\tr0=%d\n\tr1=%d\n\tr2=%d\n\tr3=%d", r0, r1, r2, r3);

      $write("Final state of memory:");
      for (i=0; i< 16; i=i+1) begin
        if (i % 4 == 0) begin
          $write("\n");
        end
        $write("\t%b", proc.MMU.memory[i]);
      end
      $write("\n");

      $finish;
   end

endmodule // E15ProcessTB

CompArch/hw5/hw5a/E15Process_tb.vcd
$date
	Fri Mar 29 00:36:33 2019
$end
$version
	Icarus Verilog
$end
$timescale
	100ps
$end
$scope module E15Process_TB $end
$var wire 4 ! dstBus [3:0] $end
$var wire 4 " mBus [3:0] $end
$var wire 2 # src [1:0] $end
$var wire 4 $ r3 [3:0] $end
$var wire 4 % r2 [3:0] $end
$var wire 4 & r1 [3:0] $end
$var wire 4 ' r0 [3:0] $end
$var wire 4 ( pc [3:0] $end
$var wire 4 ) opCode [3:0] $end
$var wire 4 * immData [3:0] $end
$var wire 2 + dst [1:0] $end
$var reg 1 , clk $end
$var integer 32 - i [31:0] $end
$scope module proc $end
$var wire 1 , clk $end
$var wire 4 . dstBus [3:0] $end
$var wire 4 / mBus [3:0] $end
$var wire 1 0 zVal $end
$var wire 4 1 resVal [3:0] $end
$var wire 1 2 pcz $end
$var wire 4 3 pcRes [3:0] $end
$var wire 4 4 mmuValueOut [3:0] $end
$var reg 1 5 addNotSub $end
$var reg 4 6 aluOut [3:0] $end
$var reg 4 7 dbEn [3:0] $end
$var reg 2 8 dst [1:0] $end
$var reg 4 9 immData [3:0] $end
$var reg 4 : mbEn [3:0] $end
$var reg 1 ; mmuControl $end
$var reg 2 < myState [1:0] $end
$var reg 4 = opCode [3:0] $end
$var reg 4 > pc [3:0] $end
$var reg 4 ? pcIncr [3:0] $end
$var reg 4 @ r0 [3:0] $end
$var reg 4 A r1 [3:0] $end
$var reg 4 B r2 [3:0] $end
$var reg 4 C r3 [3:0] $end
$var reg 2 D src [1:0] $end
$var reg 1 E zFlag $end
$scope module MMU $end
$var wire 4 F address [3:0] $end
$var wire 1 , clk $end
$var wire 4 G valueIn [3:0] $end
$var wire 4 H valueOut [3:0] $end
$var wire 1 ; write_enable $end
$upscope $end
$scope module dataALU $end
$var wire 1 5 addNotSub $end
$var wire 4 I dst [3:0] $end
$var wire 4 J src [3:0] $end
$var wire 1 0 zFlag $end
$var wire 4 K res [3:0] $end
$upscope $end
$scope module pcALU $end
$var wire 1 L addNotSub $end
$var wire 4 M dst [3:0] $end
$var wire 4 N res [3:0] $end
$var wire 4 O src [3:0] $end
$var wire 1 2 zFlag $end
$upscope $end
$upscope $end
$upscope $end
$enddefinitions $end
#0
$dumpvars
b0 O
bx N
bx M
1L
bx K
bx J
bx I
bx H
bx G
bx F
xE
bx D
bx C
bx B
bx A
bx @
bx ?
b0 >
bx =
b0 <
x;
bx :
bx 9
bx 8
bx 7
bx 6
x5
bx 4
bx 3
x2
bx 1
x0
bx /
bx .
bx -
0,
bx +
bx *
bx )
b0 (
bx '
bx &
bx %
bx $
bx #
bx "
bx !
$end
#10
b1 <
0;
b1001 )
b1001 =
b0 #
b0 D
b0 +
b0 8
b0 *
b0 9
1,
#20
0,
#30
b0 4
b0 H
b0 "
b0 /
b0 F
b0 J
b10 <
05
b0 7
b101 :
1,
#40
0,
#50
b11 <
02
b1 3
b1 N
b1 ?
b1 M
1,
#60
0,
#70
10
b0 1
b0 K
b0 !
b0 .
b0 G
b0 I
b0 <
b10 3
b10 N
b1 (
b1 >
b1 O
b0 '
b0 @
1,
#80
0,
#90
b1 <
b1 +
b1 8
1,
#100
0,
#110
x0
bx 1
bx K
bx !
bx .
bx G
bx I
b10 <
b1 7
1,
#120
0,
#130
b11 <
1,
#140
0,
#150
10
b0 1
b0 K
b0 !
b0 .
b0 G
b0 I
b0 <
b11 3
b11 N
b10 (
b10 >
b10 O
b0 &
b0 A
1,
#160
0,
#170
b1 <
b100 )
b100 =
b1 #
b1 D
b11 +
b11 8
1,
#180
0,
#190
x0
bx 1
bx K
bx !
bx .
bx G
bx I
b0 4
b0 H
b0 "
b0 /
b0 F
b0 J
b10 <
b11 7
b1 :
1,
#200
0,
#210
b11 <
b0 6
b100 :
1,
#220
0,
#230
10
b0 1
b0 K
b0 !
b0 .
b0 G
b0 I
b0 <
b100 3
b100 N
b11 (
b11 >
b11 O
b0 $
b0 C
1,
#240
0,
#250
b1 <
b1010 )
b1010 =
b11 #
b11 D
b0 +
b0 8
1,
#260
0,
#270
b0 !
b0 .
b0 G
b0 I
b0 4
b0 H
b0 "
b0 /
b0 F
b0 J
b10 <
15
b0 7
b11 :
1,
#280
0,
#290
b11 <
1E
b100 :
1,
#300
0,
#310
b0 <
b101 3
b101 N
b100 (
b100 >
b100 O
1,
#320
0,
#330
b1 <
b1011 )
b1011 =
b0 #
b0 D
b1 +
b1 8
b1 *
b1 9
1,
#340
0,
#350
00
b1 1
b1 K
b100 4
b100 H
b1 "
b1 /
b1 F
b1 J
b10 <
b1 7
b101 :
1,
#360
0,
#370
b11 <
0E
b1 6
b100 :
1,
#380
0,
#390
b10 1
b10 K
b1 !
b1 .
b1 G
b1 I
b0 <
b110 3
b110 N
b101 (
b101 >
b101 O
b1 &
b1 A
1,
#400
0,
#410
b1 <
b100 )
b100 =
b1 #
b1 D
b0 *
b0 9
1,
#420
0,
#430
10
b0 1
b0 K
b100 4
b100 H
b1 "
b1 /
b1 F
b1 J
b10 <
05
b1 :
1,
#440
0,
#450
00
b1101 1
b1101 K
b1 4
b1 H
b100 "
b100 /
b100 F
b100 J
b11 <
b100 6
b100 :
1,
#460
0,
#470
10
b0 1
b0 K
b100 !
b100 .
b100 G
b100 I
b0 <
b111 3
b111 N
b110 (
b110 >
b110 O
b100 &
b100 A
1,
#480
0,
#490
b1 <
b1111 )
b1111 =
b0 #
b0 D
b1111 *
b1111 9
1,
#500
0,
#510
00
b101 1
b101 K
b1010 4
b1010 H
b1111 "
b1111 /
b1111 F
b1111 J
b10 <
b101 :
1,
#520
0,
#530
b1111 1
b1111 K
b1110 4
b1110 H
b101 "
b101 /
b101 F
b101 J
b11 <
b101 6
b100 :
1,
#540
0,
#550
b0 <
b1000 3
b1000 N
b111 (
b111 >
b111 O
1,
#560
0,
#570
b1 <
b11 )
b11 =
b0 +
b0 8
b1011 *
b1011 9
1,
#580
0,
#590
b1011 1
b1011 K
b0 !
b0 .
b0 G
b0 I
b10 <
b0 7
1,
#600
0,
#610
b11 <
b10 3
b10 N
b1011 ?
b1011 M
1,
#620
0,
#630
b0 <
b1101 3
b1101 N
b10 (
b10 >
b10 O
1,
#640
0,
#650
b1 <
b100 )
b100 =
b1 #
b1 D
b11 +
b11 8
b0 *
b0 9
1,
#660
0,
#670
b1100 1
b1100 K
b1 4
b1 H
b100 "
b100 /
b100 F
b100 J
b10 <
b11 7
b1 :
1,
#680
0,
#690
b1111 1
b1111 K
b100 4
b100 H
b1 "
b1 /
b1 F
b1 J
b11 <
b1 6
b100 :
b11 3
b11 N
b1 ?
b1 M
1,
#700
0,
#710
10
b0 1
b0 K
b1 !
b1 .
b1 G
b1 I
b0 <
b100 3
b100 N
b11 (
b11 >
b11 O
b1 $
b1 C
1,
#720
0,
#730
b1 <
b1010 )
b1010 =
b11 #
b11 D
b0 +
b0 8
1,
#740
0,
#750
00
b1 1
b1 K
b0 !
b0 .
b0 G
b0 I
b100 4
b100 H
b1 "
b1 /
b1 F
b1 J
b10 <
15
b0 7
b11 :
1,
#760
0,
#770
b11 <
b100 :
1,
#780
0,
#790
b10 1
b10 K
b1 !
b1 .
b1 G
b1 I
b0 <
b101 3
b101 N
b100 (
b100 >
b100 O
b1 '
b1 @
1,
#800
0,
#810
b1 <
b1011 )
b1011 =
b0 #
b0 D
b1 +
b1 8
b1 *
b1 9
1,
#820
0,
#830
b101 1
b101 K
b100 !
b100 .
b100 G
b100 I
b100 4
b100 H
b1 "
b1 /
b1 F
b1 J
b10 <
b1 7
b101 :
1,
#840
0,
#850
b1001 1
b1001 K
b1110 4
b1110 H
b101 "
b101 /
b101 F
b101 J
b11 <
b101 6
b100 :
1,
#860
0,
#870
b1010 1
b1010 K
b101 !
b101 .
b101 G
b101 I
b0 <
b110 3
b110 N
b101 (
b101 >
b101 O
b101 &
b101 A
1,
#880
0,
#890
b1 <
b100 )
b100 =
b1 #
b1 D
b0 *
b0 9
1,
#900
0,
#910
10
b0 1
b0 K
b1110 4
b1110 H
b101 "
b101 /
b101 F
b101 J
b10 <
05
b1 :
1,
#920
0,
#930
00
b111 1
b111 K
b0 4
b0 H
b1110 "
b1110 /
b1110 F
b1110 J
b11 <
b1110 6
b100 :
1,
#940
0,
#950
10
b0 1
b0 K
b1110 !
b1110 .
b1110 G
b1110 I
b0 <
b111 3
b111 N
b110 (
b110 >
b110 O
b1110 &
b1110 A
1,
#960
0,
#970
b1 <
b1111 )
b1111 =
b0 #
b0 D
b1111 *
b1111 9
1,
#980
0,
#990
00
b1111 1
b1111 K
b1010 4
b1010 H
b1111 "
b1111 /
b1111 F
b1111 J
b10 <
b101 :
1,
#1000
0,
#1010
b11 <
b1111 6
b100 :
1,
#1020
0,
#1030
b0 <
b1000 3
b1000 N
b111 (
b111 >
b111 O
1,
#1040
0,
#1050
b1 <
b11 )
b11 =
b0 +
b0 8
b1011 *
b1011 9
1,
#1060
0,
#1070
b10 1
b10 K
b1 !
b1 .
b1 G
b1 I
b10 <
b0 7
1,
#1080
0,
#1090
b11 <
b10 3
b10 N
b1011 ?
b1011 M
1,
#1100
0,
#1110
b0 <
b1101 3
b1101 N
b10 (
b10 >
b10 O
1,
#1120
0,
#1130
b1 <
b100 )
b100 =
b1 #
b1 D
b11 +
b11 8
b0 *
b0 9
1,
#1140
0,
#1150
b11 1
b11 K
b0 4
b0 H
b1110 "
b1110 /
b1110 F
b1110 J
b10 <
b11 7
b1 :
1,
#1160
0,
#1170
b1 1
b1 K
b0 4
b0 H
b0 "
b0 /
b0 F
b0 J
b11 <
b0 6
b100 :
b11 3
b11 N
b1 ?
b1 M
1,
#1180
0,
#1190
10
b0 1
b0 K
b0 !
b0 .
b0 G
b0 I
b0 <
b100 3
b100 N
b11 (
b11 >
b11 O
b0 $
b0 C
1,
#1200
0,
#1210
b1 <
b1010 )
b1010 =
b11 #
b11 D
b0 +
b0 8
1,
#1220
0,
#1230
00
b1 1
b1 K
b1 !
b1 .
b1 G
b1 I
b0 4
b0 H
b0 "
b0 /
b0 F
b0 J
b10 <
15
b0 7
b11 :
1,
#1240
0,
#1250
b10 1
b10 K
b100 4
b100 H
b1 "
b1 /
b1 F
b1 J
b11 <
b1 6
b100 :
1,
#1260
0,
#1270
b0 <
b101 3
b101 N
b100 (
b100 >
b100 O
1,
#1280
0,
#1290
b1 <
b1011 )
b1011 =
b0 #
b0 D
b1 +
b1 8
b1 *
b1 9
1,
#1300
0,
#1310
b1111 1
b1111 K
b1110 !
b1110 .
b1110 G
b1110 I
b100 4
b100 H
b1 "
b1 /
b1 F
b1 J
b10 <
b1 7
b101 :
1,
#1320
0,
#1330
b1101 1
b1101 K
b1010 4
b1010 H
b1111 "
b1111 /
b1111 F
b1111 J
b11 <
b1111 6
b100 :
1,
#1340
0,
#1350
b1110 1
b1110 K
b1111 !
b1111 .
b1111 G
b1111 I
b0 <
b110 3
b110 N
b101 (
b101 >
b101 O
b1111 &
b1111 A
1,
#1360
0,
#1370
b1 <
b100 )
b100 =
b1 #
b1 D
b0 *
b0 9
1,
#1380
0,
#1390
10
b0 1
b0 K
b1010 4
b1010 H
b1111 "
b1111 /
b1111 F
b1111 J
b10 <
05
b1 :
1,
#1400
0,
#1410
00
b101 1
b101 K
b10 4
b10 H
b1010 "
b1010 /
b1010 F
b1010 J
b11 <
b1010 6
b100 :
1,
#1420
0,
#1430
10
b0 1
b0 K
b1010 !
b1010 .
b1010 G
b1010 I
b0 <
b111 3
b111 N
b110 (
b110 >
b110 O
b1010 &
b1010 A
1,
#1440
0,
#1450
b1 <
b1111 )
b1111 =
b0 #
b0 D
b1111 *
b1111 9
1,
#1460
0,
#1470
00
b1011 1
b1011 K
b1010 4
b1010 H
b1111 "
b1111 /
b1111 F
b1111 J
b10 <
b101 :
1,
#1480
0,
#1490
b1111 1
b1111 K
b110 4
b110 H
b1011 "
b1011 /
b1011 F
b1011 J
b11 <
b1011 6
b100 :
1,
#1500
0,
#1510
b0 <
b1000 3
b1000 N
b111 (
b111 >
b111 O
1,
#1520
0,
#1530
b1 <
b11 )
b11 =
b0 +
b0 8
b1011 *
b1011 9
1,
#1540
0,
#1550
b110 1
b110 K
b1 !
b1 .
b1 G
b1 I
b10 <
b0 7
1,
#1560
0,
#1570
b11 <
b10 3
b10 N
b1011 ?
b1011 M
1,
#1580
0,
#1590
b0 <
b1101 3
b1101 N
b10 (
b10 >
b10 O
1,
#1600
0,
#1610
b1 <
b100 )
b100 =
b1 #
b1 D
b11 +
b11 8
b0 *
b0 9
1,
#1620
0,
#1630
b0 !
b0 .
b0 G
b0 I
b10 4
b10 H
b1010 "
b1010 /
b1010 F
b1010 J
b10 <
b11 7
b1 :
1,
#1640
0,
#1650
b1110 1
b1110 K
b1111 4
b1111 H
b10 "
b10 /
b10 F
b10 J
b11 <
b10 6
b100 :
b11 3
b11 N
b1 ?
b1 M
1,
#1660
0,
#1670
10
b0 1
b0 K
b10 !
b10 .
b10 G
b10 I
b0 <
b100 3
b100 N
b11 (
b11 >
b11 O
b10 $
b10 C
1,
#1680
0,
#1690
b1 <
b1010 )
b1010 =
b11 #
b11 D
b0 +
b0 8
1,
#1700
0,
#1710
00
b11 1
b11 K
b1 !
b1 .
b1 G
b1 I
b1111 4
b1111 H
b10 "
b10 /
b10 F
b10 J
b10 <
15
b0 7
b11 :
1,
#1720
0,
#1730
b100 1
b100 K
b11 4
b11 H
b11 "
b11 /
b11 F
b11 J
b11 <
b11 6
b100 :
1,
#1740
0,
#1750
b110 1
b110 K
b11 !
b11 .
b11 G
b11 I
b0 <
b101 3
b101 N
b100 (
b100 >
b100 O
b11 '
b11 @
1,
#1760
0,
#1770
b1 <
b1011 )
b1011 =
b0 #
b0 D
b1 +
b1 8
b1 *
b1 9
1,
#1780
0,
#1790
b1011 1
b1011 K
b1010 !
b1010 .
b1010 G
b1010 I
b100 4
b100 H
b1 "
b1 /
b1 F
b1 J
b10 <
b1 7
b101 :
1,
#1800
0,
#1810
b101 1
b101 K
b110 4
b110 H
b1011 "
b1011 /
b1011 F
b1011 J
b11 <
b1011 6
b100 :
1,
#1820
0,
#1830
b110 1
b110 K
b1011 !
b1011 .
b1011 G
b1011 I
b0 <
b110 3
b110 N
b101 (
b101 >
b101 O
b1011 &
b1011 A
1,
#1840
0,
#1850
b1 <
b100 )
b100 =
b1 #
b1 D
b0 *
b0 9
1,
#1860
0,
#1870
10
b0 1
b0 K
b110 4
b110 H
b1011 "
b1011 /
b1011 F
b1011 J
b10 <
05
b1 :
1,
#1880
0,
#1890
00
b101 1
b101 K
b110 4
b110 H
b110 "
b110 /
b110 F
b110 J
b11 <
b110 6
b100 :
1,
#1900
0,
#1910
10
b0 1
b0 K
b110 !
b110 .
b110 G
b110 I
b0 <
b111 3
b111 N
b110 (
b110 >
b110 O
b110 &
b110 A
1,
#1920
0,
#1930
b1 <
b1111 )
b1111 =
b0 #
b0 D
b1111 *
b1111 9
1,
#1940
0,
#1950
00
b111 1
b111 K
b1010 4
b1010 H
b1111 "
b1111 /
b1111 F
b1111 J
b10 <
b101 :
1,
#1960
0,
#1970
b1111 1
b1111 K
b1111 4
b1111 H
b111 "
b111 /
b111 F
b111 J
b11 <
b111 6
b100 :
1,
#1980
0,
#1990
b0 <
b1000 3
b1000 N
b111 (
b111 >
b111 O
1,
#2000
0,
#2010
b1 <
b11 )
b11 =
b0 +
b0 8
b1011 *
b1011 9
1,
#2020
0,
#2030
b1100 1
b1100 K
b11 !
b11 .
b11 G
b11 I
b10 <
b0 7
1,
#2040
0,
#2050
b11 <
b10 3
b10 N
b1011 ?
b1011 M
1,
#2060
0,
#2070
b0 <
b1101 3
b1101 N
b10 (
b10 >
b10 O
1,
#2080
0,
#2090
b1 <
b100 )
b100 =
b1 #
b1 D
b11 +
b11 8
b0 *
b0 9
1,
#2100
0,
#2110
b10 !
b10 .
b10 G
b10 I
b110 4
b110 H
b110 "
b110 /
b110 F
b110 J
b10 <
b11 7
b1 :
1,
#2120
0,
#2130
b11 <
b110 6
b100 :
b11 3
b11 N
b1 ?
b1 M
1,
#2140
0,
#2150
10
b0 1
b0 K
b110 !
b110 .
b110 G
b110 I
b0 <
b100 3
b100 N
b11 (
b11 >
b11 O
b110 $
b110 C
1,
#2160
0,
#2170
b1 <
b1010 )
b1010 =
b11 #
b11 D
b0 +
b0 8
1,
#2180
0,
#2190
00
b1001 1
b1001 K
b11 !
b11 .
b11 G
b11 I
b110 4
b110 H
b110 "
b110 /
b110 F
b110 J
b10 <
15
b0 7
b11 :
1,
#2200
0,
#2210
b1100 1
b1100 K
b0 4
b0 H
b1001 "
b1001 /
b1001 F
b1001 J
b11 <
b1001 6
b100 :
1,
#2220
0,
#2230
b10 1
b10 K
b1001 !
b1001 .
b1001 G
b1001 I
b0 <
b101 3
b101 N
b100 (
b100 >
b100 O
b1001 '
b1001 @
1,
#2240
0,
#2250
b1 <
b1011 )
b1011 =
b0 #
b0 D
b1 +
b1 8
b1 *
b1 9
1,
#2260
0,
#2270
b111 1
b111 K
b110 !
b110 .
b110 G
b110 I
b100 4
b100 H
b1 "
b1 /
b1 F
b1 J
b10 <
b1 7
b101 :
1,
#2280
0,
#2290
b1101 1
b1101 K
b1111 4
b1111 H
b111 "
b111 /
b111 F
b111 J
b11 <
b111 6
b100 :
1,
#2300
0,
#2310
b1110 1
b1110 K
b111 !
b111 .
b111 G
b111 I
b0 <
b110 3
b110 N
b101 (
b101 >
b101 O
b111 &
b111 A
1,
#2320
0,
#2330
b1 <
b100 )
b100 =
b1 #
b1 D
b0 *
b0 9
1,
#2340
0,
#2350
10
b0 1
b0 K
b1111 4
b1111 H
b111 "
b111 /
b111 F
b111 J
b10 <
05
b1 :
1,
#2360
0,
#2370
00
b1000 1
b1000 K
b1010 4
b1010 H
b1111 "
b1111 /
b1111 F
b1111 J
b11 <
b1111 6
b100 :
1,
#2380
0,
#2390
10
b0 1
b0 K
b1111 !
b1111 .
b1111 G
b1111 I
b0 <
b111 3
b111 N
b110 (
b110 >
b110 O
b1111 &
b1111 A
1,
#2400
0,
#2410
b1 <
b1111 )
b1111 =
b0 #
b0 D
b1111 *
b1111 9
1,
#2420
0,
#2430
b1010 4
b1010 H
b1111 "
b1111 /
b1111 F
b1111 J
b10 <
b101 :
1,
#2440
0,
#2450
00
b1111 1
b1111 K
b0 4
b0 H
b0 "
b0 /
b0 F
b0 J
b11 <
1E
b0 6
b100 :
1,
#2460
0,
#2470
b0 <
b1000 3
b1000 N
b111 (
b111 >
b111 O
1,
#2480
0,
#2490
b1 <
b11 )
b11 =
b0 +
b0 8
b1011 *
b1011 9
1,
#2500
0,
#2510
b1001 1
b1001 K
b1001 !
b1001 .
b1001 G
b1001 I
b10 <
b0 7
1,
#2520
0,
#2530
b11 <
1,
#2540
0,
#2550
b0 <
b1001 3
b1001 N
b1000 (
b1000 >
b1000 O
1,
#2560
0,
#2570
b1 <
b0 )
b0 =
b0 *
b0 9
1,
#2580
0,
#2590
b10 <
1,
#2600
0,
#2610
b11 <
b1000 3
b1000 N
b0 ?
b0 M
1,
#2620
0,
#2630
b0 <
1,
#2640
0,
#2650
b1 <
1,
#2660
0,
#2670
b10 <
1,
#2680
0,
#2690
b11 <
1,
#2700
0,
#2710
b0 <
1,
#2720
0,
#2730
b1 <
1,
#2740
0,
#2750
b10 <
1,
#2760
0,
#2770
b11 <
1,
#2780
0,
#2790
b0 <
1,
#2800
0,
#2810
b1 <
1,
#2820
0,
#2830
b10 <
1,
#2840
0,
#2850
b11 <
1,
#2860
0,
#2870
b0 <
1,
#2880
0,
#2890
b1 <
1,
#2900
0,
#2910
b10 <
1,
#2920
0,
#2930
b11 <
1,
#2940
0,
#2950
b0 <
1,
#2960
0,
#2970
b1 <
1,
#2980
0,
#2990
b10 <
1,
#3000
0,
#3010
b11 <
1,
#3020
0,
#3030
b0 <
1,
#3040
0,
#3050
b1 <
1,
#3060
0,
#3070
b10 <
1,
#3080
0,
#3090
b11 <
1,
#3100
0,
#3110
b0 <
1,
#3120
0,
#3130
b1 <
1,
#3140
0,
#3150
b10 <
1,
#3160
0,
#3170
b11 <
1,
#3180
0,
#3190
b0 <
1,
#3200
0,
#3210
b1 <
1,
#3220
0,
#3230
b10 <
1,
#3240
0,
#3250
b11 <
1,
#3260
0,
#3270
b0 <
1,
#3280
0,
#3290
b1 <
1,
#3300
0,
#3310
b10 <
1,
#3320
0,
#3330
b11 <
1,
#3340
0,
#3350
b0 <
1,
#3360
0,
#3370
b1 <
1,
#3380
0,
#3390
b10 <
1,
#3400
0,
#3410
b11 <
1,
#3420
0,
#3430
b0 <
1,
#3440
0,
#3450
b1 <
1,
#3460
0,
#3470
b10 <
1,
#3480
0,
#3490
b11 <
1,
#3500
0,
#3510
b0 <
1,
#3520
0,
#3530
b1 <
1,
#3540
0,
#3550
b10 <
1,
#3560
0,
#3570
b11 <
1,
#3580
0,
#3590
b0 <
1,
#3600
0,
#3610
b1 <
1,
#3620
0,
#3630
b10 <
1,
#3640
0,
#3650
b11 <
1,
#3660
0,
#3670
b0 <
1,
#3680
0,
#3690
b1 <
1,
#3700
0,
#3710
b10 <
1,
#3720
0,
#3730
b11 <
1,
#3740
0,
#3750
b0 <
1,
#3760
0,
#3770
b1 <
1,
#3780
0,
#3790
b10 <
1,
#3800
0,
#3810
b11 <
1,
#3820
0,
#3830
b0 <
1,
#3840
0,
#3850
b1 <
1,
#3860
0,
#3870
b10 <
1,
#3880
0,
#3890
b11 <
1,
#3900
0,
#3910
b0 <
1,
#3920
0,
#3930
b1 <
1,
#3940
0,
#3950
b10 <
1,
#3960
0,
#3970
b11 <
1,
#3980
0,
#3990
b0 <
1,
#4000
0,
#4010
b1 <
1,
#4020
0,
#4030
b10 <
1,
#4040
0,
#4050
b11 <
1,
#4060
0,
#4070
b0 <
1,
#4080
0,
#4090
b1 <
1,
#4100
0,
#4110
b10 <
1,
#4120
0,
#4130
b11 <
1,
#4140
0,
#4150
b0 <
1,
#4160
0,
#4170
b1 <
1,
#4180
0,
#4190
b10 <
1,
#4200
0,
#4210
b11 <
1,
#4220
0,
#4230
b0 <
1,
#4240
0,
#4250
b1 <
1,
