CompArch/hw5/hw5b/muldemo.v
/*          OPCODE SRC  DST  IMMDATA */
myROM[0]  = {movi, RXX, Rg0, 4'b0011};
myROM[1]  = {movi, RXX, Rg1, 4'b0100};
myROM[2]  = {mul,  Rg0, Rg1, 4'b0011};
myROM[3]  = {movi, RXX, Rg0, 4'b0010};
myROM[4]  = {movi, RXX, Rg2, 4'b0111};
myROM[5] =  {mul,  Rg0, Rg2, 4'b0000};
myROM[6] =  {jmp,  RXX, RXX, 4'b0000};
myROM[7] =  {jmp,  RXX, RXX, 4'b0000};
myROM[8] =  {jmp,  RXX, RXX, 4'b0000};
myROM[9] =  {jmp,  RXX, RXX, 4'b0000};
myROM[10] = {jmp,  RXX, RXX, 4'b0000};
myROM[11] = {jmp,  RXX, RXX, 4'b0000};
myROM[12] = {jmp,  RXX, RXX, 4'b0000};
myROM[13] = {jmp,  RXX, RXX, 4'b0000};
myROM[14] = {jmp,  RXX, RXX, 4'b0000};
myROM[15] = {jmp,  RXX, RXX, 4'b0000};

CompArch/hw5/hw5b/E15Process_mc.v
`default_nettype none

module E15Process(input clk,
                  output reg [3:0] pc,             // Program Counter
                  output reg [3:0] opCode,         // op code
                  output reg [1:0] src, dst,       // src and dst register
                  output reg [3:0] immData,        // "Immediate" data
                  output reg [3:0] r0, r1, r2, r3, // Registers
                  output tri [3:0] mBus, dstBus    // Buses
                  );

   parameter fetch=2'd0, decode=2'd1, exec=2'd2, store=2'd3;

   parameter Rg0 = 2'b00, Rg1 = 2'b01, Rg2 = 2'b10, Rg3 = 2'b11,
             RXX = 2'b00;

   parameter
     jmp  = 4'b0000, jz   = 4'b0010,  jnz = 4'b0011,
     movi = 4'b1001, mov  = 4'b1000,
     addi = 4'b1011, add  = 4'b1010,
     subi = 4'b1101, sub  = 4'b1100,
     cmpi = 4'b1111, cmp  = 4'b1110,

     mul = 4'b0100,
     quadruple = 4'b0001,
     clearall = 4'b0101,
     increg = 4'b0111;

   parameter   hiZ = 4'bz;

   parameter   bEn_R0 = 3'd0, bEn_R1 = 3'd1,
     bEn_R2 = 3'd2, bEn_R3 = 3'd3,
     bEn_ALU = 3'd4, bEn_Imm = 3'd5;

   reg  [3:0] pcIncr; // Program Counter Increment
   wire [3:0] pcRes;  // Output of pc ALU
   wire [3:0] microcodePcRes;
   wire       pcz;    // Unused - zero flag for pc ALU
   wire [11:0] currentInstruction;

   reg [1:0]  myState;      // State (phase of excution)
   reg [11:0] myROM [15:0]; // ROM (holds program)
   reg [3:0]  mbEn, dbEn;   // Used to determine which tri-state buffers are
                            // enabled for master bus and destination bus.

   reg        addNotSub; // Determines if ALU adds or subtracts
   reg [3:0]  aluOut;    // Register to hold output of main ALU
   reg        zFlag;     // Zero flag
   wire [3:0] resVal;    // Output (combinational) of ALU
   wire       zVal;      // Output (combinational) of ALU zero flag

   reg [3:0] microcodePc;
   reg microcodeEnable = 1'b0;
   reg [11:0] microcodeBuffer [15:0]; // holds microcode, if applicable
   assign currentInstruction = microcodeEnable ? microcodeBuffer[microcodePc] : myROM[pc];
   parameter end_of_microcode = {jmp, RXX, RXX, 4'b0000};

   initial
     begin

        `include "muldemo.v"

        pc = 4'b0000;
        myState = fetch;

     end

   always @(posedge clk)
     case(myState)
       fetch:
         begin
            {opCode, src, dst, immData} = currentInstruction;

            if (microcodeEnable && currentInstruction == end_of_microcode)
              begin
                microcodeEnable <= 0;
                pc <= pcRes;
                pcIncr <= 4'd1;
              end
            else
              case (opCode)

                // multiply the value in src by dst and store result in dst
                mul:
                  begin
                    microcodePc <= 4'd0;
                    microcodeEnable <= 1'b1;
                    microcodeBuffer[0] <= {movi,RXX, Rg3, 4'b0000};
                    microcodeBuffer[1] <= {cmpi,RXX, src, 4'b0000};
                    microcodeBuffer[2] <= {jz,  RXX, RXX, 4'b0100};
                    microcodeBuffer[3] <= {add, dst, Rg3, 4'b0000};
                    microcodeBuffer[4] <= {subi,RXX, src, 4'b0001};
                    microcodeBuffer[5] <= {jnz, RXX, RXX, 4'b1110};
                    microcodeBuffer[6] <= {mov, Rg3, dst, 4'b0000};
                    microcodeBuffer[7] <= {movi,RXX, Rg3, 4'b0000};
                    microcodeBuffer[8] <= end_of_microcode;
                  end

                // set all registers to 0
                clearall:
                  begin
                    microcodePc <= 4'd0;
                    microcodeEnable <= 1'b1;
                    microcodeBuffer[0] <= {movi,RXX, Rg0, 4'b0000};
                    microcodeBuffer[1] <= {movi,RXX, Rg1, 4'b0000};
                    microcodeBuffer[2] <= {movi,RXX, Rg2, 4'b0000};
                    microcodeBuffer[3] <= {movi,RXX, Rg3, 4'b0000};
                    microcodeBuffer[4] <= end_of_microcode;
                  end

                // quadruple the value in src, storing the result in dst
                quadruple:
                  begin
                    microcodePc <= 4'd0;
                    microcodeEnable <= 1'b1;
                    microcodeBuffer[0] <= {mov, src, dst, 4'b0000};
                    microcodeBuffer[1] <= {add, dst, dst, 4'b0000};
                    microcodeBuffer[2] <= {add, dst, dst, 4'b0000};
                    microcodeBuffer[3] <= end_of_microcode;
                  end

                increg:
                  begin
                    microcodePc <= 4'd0;
                    microcodeEnable <= 1'b1;
                    microcodeBuffer[0] <= {cmpi, RXX, dst, 4'b0000};
                    microcodeBuffer[1] <= {jz,   RXX, RXX, 4'b0111};
                    microcodeBuffer[2] <= {cmpi, RXX, dst, 4'b0001};
                    microcodeBuffer[3] <= {jz,   RXX, RXX, 4'b0111};
                    microcodeBuffer[4] <= {cmpi, RXX, dst, 4'b0010};
                    microcodeBuffer[5] <= {jz,   RXX, RXX, 4'b0111};
                    microcodeBuffer[6] <= {addi, RXX, Rg3, 4'b0001};
                    microcodeBuffer[7] <= end_of_microcode;
                    microcodeBuffer[8] <= {addi, RXX, Rg0, 4'b0001};
                    microcodeBuffer[9] <= end_of_microcode;
                    microcodeBuffer[10] <= {addi, RXX, Rg1, 4'b0001};
                    microcodeBuffer[11] <= end_of_microcode;
                    microcodeBuffer[12] <= {addi, RXX, Rg2, 4'b0001};
                    microcodeBuffer[13] <= end_of_microcode;
                  end
                default:
                  myState <= decode;
              endcase
         end

       decode:
         begin
            case(opCode)
              movi, addi, subi, cmpi:
                begin
                   mbEn <= bEn_Imm;
                end
              mov, add, sub, cmp:
                case(src)
                  Rg0: mbEn <= bEn_R0;
                  Rg1: mbEn <= bEn_R1;
                  Rg2: mbEn <= bEn_R2;
                  Rg3: mbEn <= bEn_R3;
                endcase
            endcase

            case(dst)
              Rg0: dbEn <= bEn_R0;
              Rg1: dbEn <= bEn_R1;
              Rg2: dbEn <= bEn_R2;
              Rg3: dbEn <= bEn_R3;
            endcase

            addNotSub <= ((opCode == add) | (opCode == addi));
            myState <= exec;
         end

       exec:
         begin
            case(opCode)
              addi, add, subi, sub, cmpi, cmp:
                begin
                   pcIncr <= 4'd1;
                   mbEn <= bEn_ALU;
                   aluOut <= resVal;
                   zFlag <= zVal;
                end
              jmp: pcIncr <= immData;
              jz:  pcIncr <= zFlag ? immData : 4'd1;
              jnz: pcIncr <= zFlag ? 4'd1 : immData;
              default: pcIncr <= 4'd1;
            endcase
            myState <= store;
         end

       store:
         begin
            case(opCode)
              movi, mov, add, addi, sub, subi:
                case(dst)
                  Rg0: r0 <= mBus;
                  Rg1: r1 <= mBus;
                  Rg2: r2 <= mBus;
                  Rg3: r3 <= mBus;
                endcase
            endcase

            if (microcodeEnable)
              microcodePc <= microcodePcRes;
            else
              pc <= pcRes;
            myState <= fetch;
         end

     endcase

   assign mBus = (mbEn==bEn_R0)  ? r0      : hiZ;
   assign mBus = (mbEn==bEn_R1)  ? r1      : hiZ;
   assign mBus = (mbEn==bEn_R2)  ? r2      : hiZ;
   assign mBus = (mbEn==bEn_R3)  ? r3      : hiZ;
   assign mBus = (mbEn==bEn_Imm) ? immData : hiZ;
   assign mBus = (mbEn==bEn_ALU) ? aluOut  : hiZ;

   assign dstBus = (dbEn==bEn_R0)  ? r0 : hiZ;
   assign dstBus = (dbEn==bEn_R1)  ? r1 : hiZ;
   assign dstBus = (dbEn==bEn_R2)  ? r2 : hiZ;
   assign dstBus = (dbEn==bEn_R3)  ? r3 : hiZ;

   simpleALU dataALU(addNotSub, mBus, dstBus, zVal, resVal);
   simpleALU pcALU(1'b1, pc, pcIncr, pcz, pcRes);
   simpleALU microcodePcALU(1'b1, microcodePc, pcIncr, pcz, microcodePcRes);

endmodule


module simpleALU(
    input addNotSub,
    input [3:0] src, dst,
    output zFlag,
    output [3:0] res);
    assign res = addNotSub ? dst + src : dst - src;
    assign zFlag = !(res);

endmodule

CompArch/hw5/hw5b/E15Process_mc_tb.v
`timescale 1ns/100ps
`include "E15Process_mc.v"

module E15Process_TB;

   reg clk = 0;

   wire [3:0] pc;
   wire [3:0] opCode;
   wire [1:0] src, dst;
   wire [3:0] immData;
   wire [3:0] r0, r1, r2, r3;
   tri [3:0]  mBus, dstBus;

   E15Process proc(clk, pc, opCode, src, dst, immData, 
                   r0, r1, r2, r3, mBus, dstBus);

   always #1
     clk = ~clk;

   initial begin
      $dumpfile("E15Process_tb.vcd");
      $dumpvars(0, E15Process_TB);
      #1000

      $display("Final state of register file:\n\tr0=%d\n\tr1=%d\n\tr2=%d\n\tr3=%d", r0, r1, r2, r3);

      $finish;
   end

endmodule // E15ProcessTB

CompArch/hw5/hw5b/E15Process_tb.vcd
$date
	Fri Mar 29 13:55:38 2019
$end
$version
	Icarus Verilog
$end
$timescale
	100ps
$end
$scope module E15Process_TB $end
$var wire 4 ! dstBus [3:0] $end
$var wire 4 " mBus [3:0] $end
$var wire 2 # src [1:0] $end
$var wire 4 $ r3 [3:0] $end
$var wire 4 % r2 [3:0] $end
$var wire 4 & r1 [3:0] $end
$var wire 4 ' r0 [3:0] $end
$var wire 4 ( pc [3:0] $end
$var wire 4 ) opCode [3:0] $end
$var wire 4 * immData [3:0] $end
$var wire 2 + dst [1:0] $end
$var reg 1 , clk $end
$scope module proc $end
$var wire 1 , clk $end
$var wire 4 - dstBus [3:0] $end
$var wire 4 . mBus [3:0] $end
$var wire 1 / pcz $end
$var wire 1 0 zVal $end
$var wire 4 1 resVal [3:0] $end
$var wire 4 2 pcRes [3:0] $end
$var wire 4 3 microcodePcRes [3:0] $end
$var wire 12 4 currentInstruction [11:0] $end
$var reg 1 5 addNotSub $end
$var reg 4 6 aluOut [3:0] $end
$var reg 4 7 dbEn [3:0] $end
$var reg 2 8 dst [1:0] $end
$var reg 4 9 immData [3:0] $end
$var reg 4 : mbEn [3:0] $end
$var reg 1 ; microcodeEnable $end
$var reg 4 < microcodePc [3:0] $end
$var reg 2 = myState [1:0] $end
$var reg 4 > opCode [3:0] $end
$var reg 4 ? pc [3:0] $end
$var reg 4 @ pcIncr [3:0] $end
$var reg 4 A r0 [3:0] $end
$var reg 4 B r1 [3:0] $end
$var reg 4 C r2 [3:0] $end
$var reg 4 D r3 [3:0] $end
$var reg 2 E src [1:0] $end
$var reg 1 F zFlag $end
$scope module dataALU $end
$var wire 1 5 addNotSub $end
$var wire 4 G dst [3:0] $end
$var wire 4 H src [3:0] $end
$var wire 1 0 zFlag $end
$var wire 4 I res [3:0] $end
$upscope $end
$scope module microcodePcALU $end
$var wire 1 J addNotSub $end
$var wire 4 K dst [3:0] $end
$var wire 4 L res [3:0] $end
$var wire 4 M src [3:0] $end
$var wire 1 / zFlag $end
$upscope $end
$scope module pcALU $end
$var wire 1 N addNotSub $end
$var wire 4 O dst [3:0] $end
$var wire 4 P res [3:0] $end
$var wire 4 Q src [3:0] $end
$var wire 1 / zFlag $end
$upscope $end
$upscope $end
$upscope $end
$enddefinitions $end
#0
$dumpvars
b0 Q
bx P
bx O
1N
bx M
bx L
bx K
1J
bx I
bx H
bx G
xF
bx E
bx D
bx C
bx B
bx A
bx @
b0 ?
bx >
b0 =
bx <
0;
bx :
bx 9
bx 8
bx 7
bx 6
x5
b100100000011 4
bx 3
bx 2
bx 1
x0
x/
bx .
bx -
0,
bx +
bx *
bx )
b0 (
bx '
bx &
bx %
bx $
bx #
bx "
bx !
$end
#10
b1 =
b1001 )
b1001 >
b0 #
b0 E
b0 +
b0 8
b11 *
b11 9
1,
#20
0,
#30
b11 "
b11 .
b11 H
b10 =
05
b0 7
b101 :
1,
#40
0,
#50
b11 =
b1 2
b1 P
b1 @
b1 K
b1 O
1,
#60
0,
#70
10
b0 1
b0 I
b100100010100 4
b11 !
b11 -
b11 G
b0 =
b10 2
b10 P
b1 (
b1 ?
b1 Q
b11 '
b11 A
1,
#80
0,
#90
b1 =
00
b1111 1
b1111 I
b100 "
b100 .
b100 H
b1 +
b1 8
b100 *
b100 9
1,
#100
0,
#110
x0
bx 1
bx I
bx !
bx -
bx G
b10 =
b1 7
1,
#120
0,
#130
b11 =
1,
#140
0,
#150
10
b0 1
b0 I
b10000010011 4
b100 !
b100 -
b100 G
b0 =
b11 2
b11 P
b10 (
b10 ?
b10 Q
b100 &
b100 B
1,
#160
0,
#170
b100100110000 4
1;
0/
b1 3
b1 L
b0 <
b0 M
00
b1 1
b1 I
b11 "
b11 .
b11 H
b100 )
b100 >
b11 *
b11 9
1,
#180
0,
#190
b1 =
b100 1
b100 I
b0 "
b0 .
b0 H
b1001 )
b1001 >
b11 +
b11 8
b0 *
b0 9
1,
#200
0,
#210
x0
bx 1
bx I
bx !
bx -
bx G
b10 =
b11 7
1,
#220
0,
#230
b11 =
1,
#240
0,
#250
10
b0 1
b0 I
b111100000000 4
b0 !
b0 -
b0 G
b0 =
b10 3
b10 L
b1 <
b1 M
b0 $
b0 D
1,
#260
0,
#270
b1 =
b1111 )
b1111 >
b0 +
b0 8
1,
#280
0,
#290
00
b11 1
b11 I
b11 !
b11 -
b11 G
b10 =
b0 7
1,
#300
0,
#310
10
b0 1
b0 I
b11 "
b11 .
b11 H
b11 =
0F
b11 6
b100 :
1,
#320
0,
#330
b1000000100 4
b0 =
b11 3
b11 L
b10 <
b10 M
1,
#340
0,
#350
b1 =
b10 )
b10 >
b100 *
b100 9
1,
#360
0,
#370
b10 =
1,
#380
0,
#390
b11 =
1,
#400
0,
#410
b101001110000 4
b0 =
b100 3
b100 L
b11 <
b11 M
1,
#420
0,
#430
b1 =
b1010 )
b1010 >
b1 #
b1 E
b11 +
b11 8
b0 *
b0 9
1,
#440
0,
#450
00
b100 1
b100 I
b0 !
b0 -
b0 G
b100 "
b100 .
b100 H
b10 =
15
b11 7
b1 :
1,
#460
0,
#470
b11 =
b100 6
b100 :
1,
#480
0,
#490
b1000 1
b1000 I
b110100000001 4
b100 !
b100 -
b100 G
b0 =
b101 3
b101 L
b100 <
b100 M
b100 $
b100 D
1,
#500
0,
#510
b1 =
b1101 )
b1101 >
b0 #
b0 E
b0 +
b0 8
b1 *
b1 9
1,
#520
0,
#530
b10 1
b10 I
b11 !
b11 -
b11 G
b1 "
b1 .
b1 H
b10 =
05
b0 7
b101 :
1,
#540
0,
#550
b1 1
b1 I
b10 "
b10 .
b10 H
b11 =
b10 6
b100 :
1,
#560
0,
#570
10
b0 1
b0 I
b1100001110 4
b10 !
b10 -
b10 G
b0 =
b110 3
b110 L
b101 <
b101 M
b10 '
b10 A
1,
#580
0,
#590
b1 =
b11 )
b11 >
b1110 *
b1110 9
1,
#600
0,
#610
b10 =
1,
#620
0,
#630
b11 =
b11 3
b11 L
x/
b0 2
b0 P
b1110 @
b1110 K
b1110 O
1,
#640
0,
#650
b101001110000 4
b0 =
b1 3
b1 L
b11 <
b11 M
1,
#660
0,
#670
b1 =
b1010 )
b1010 >
b1 #
b1 E
b11 +
b11 8
b0 *
b0 9
1,
#680
0,
#690
00
b1000 1
b1000 I
b100 !
b100 -
b100 G
b100 "
b100 .
b100 H
b10 =
15
b11 7
b1 :
1,
#700
0,
#710
b1100 1
b1100 I
b1000 "
b1000 .
b1000 H
b11 =
b1000 6
b100 :
b100 3
b100 L
0/
b11 2
b11 P
b1 @
b1 K
b1 O
1,
#720
0,
#730
10
b0 1
b0 I
b110100000001 4
b1000 !
b1000 -
b1000 G
b0 =
b101 3
b101 L
b100 <
b100 M
b1000 $
b1000 D
1,
#740
0,
#750
b1 =
b1101 )
b1101 >
b0 #
b0 E
b0 +
b0 8
b1 *
b1 9
1,
#760
0,
#770
00
b1 1
b1 I
b10 !
b10 -
b10 G
b1 "
b1 .
b1 H
b10 =
05
b0 7
b101 :
1,
#780
0,
#790
b11 =
b1 6
b100 :
1,
#800
0,
#810
10
b0 1
b0 I
b1100001110 4
b1 !
b1 -
b1 G
b0 =
b110 3
b110 L
b101 <
b101 M
b1 '
b1 A
1,
#820
0,
#830
b1 =
b11 )
b11 >
b1110 *
b1110 9
1,
#840
0,
#850
b10 =
1,
#860
0,
#870
b11 =
b11 3
b11 L
x/
b0 2
b0 P
b1110 @
b1110 K
b1110 O
1,
#880
0,
#890
b101001110000 4
b0 =
b1 3
b1 L
b11 <
b11 M
1,
#900
0,
#910
b1 =
b1010 )
b1010 >
b1 #
b1 E
b11 +
b11 8
b0 *
b0 9
1,
#920
0,
#930
00
b1100 1
b1100 I
b1000 !
b1000 -
b1000 G
b100 "
b100 .
b100 H
b10 =
15
b11 7
b1 :
1,
#940
0,
#950
b100 1
b100 I
b1100 "
b1100 .
b1100 H
b11 =
b1100 6
b100 :
b100 3
b100 L
0/
b11 2
b11 P
b1 @
b1 K
b1 O
1,
#960
0,
#970
b1000 1
b1000 I
b110100000001 4
b1100 !
b1100 -
b1100 G
b0 =
b101 3
b101 L
b100 <
b100 M
b1100 $
b1100 D
1,
#980
0,
#990
b1 =
b1101 )
b1101 >
b0 #
b0 E
b0 +
b0 8
b1 *
b1 9
1,
#1000
0,
#1010
10
b0 1
b0 I
b1 !
b1 -
b1 G
b1 "
b1 .
b1 H
b10 =
05
b0 7
b101 :
1,
#1020
0,
#1030
00
b1 1
b1 I
b0 "
b0 .
b0 H
b11 =
1F
b0 6
b100 :
1,
#1040
0,
#1050
10
b0 1
b0 I
b1100001110 4
b0 !
b0 -
b0 G
b0 =
b110 3
b110 L
b101 <
b101 M
b0 '
b0 A
1,
#1060
0,
#1070
b1 =
b11 )
b11 >
b1110 *
b1110 9
1,
#1080
0,
#1090
b10 =
1,
#1100
0,
#1110
b11 =
1,
#1120
0,
#1130
b100011010000 4
b0 =
b111 3
b111 L
b110 <
b110 M
1,
#1140
0,
#1150
b1 =
b1000 )
b1000 >
b11 #
b11 E
b1 +
b1 8
b0 *
b0 9
1,
#1160
0,
#1170
00
b1000 1
b1000 I
b100 !
b100 -
b100 G
b1100 "
b1100 .
b1100 H
b10 =
b1 7
b11 :
1,
#1180
0,
#1190
b11 =
1,
#1200
0,
#1210
10
b0 1
b0 I
b100100110000 4
b1100 !
b1100 -
b1100 G
b0 =
b1000 3
b1000 L
b111 <
b111 M
b1100 &
b1100 B
1,
#1220
0,
#1230
b1 =
b1001 )
b1001 >
b0 #
b0 E
b11 +
b11 8
1,
#1240
0,
#1250
00
b1100 1
b1100 I
b0 "
b0 .
b0 H
b10 =
b11 7
b101 :
1,
#1260
0,
#1270
b11 =
1,
#1280
0,
#1290
10
b0 1
b0 I
b0 4
b0 !
b0 -
b0 G
b0 =
b1001 3
b1001 L
b1000 <
b1000 M
b0 $
b0 D
1,
#1300
0,
#1310
b100100000010 4
b100 2
b100 P
b11 (
b11 ?
b11 Q
0;
b0 )
b0 >
b0 +
b0 8
1,
#1320
0,
#1330
b1 =
00
b1110 1
b1110 I
b10 "
b10 .
b10 H
b1001 )
b1001 >
b10 *
b10 9
1,
#1340
0,
#1350
b0 !
b0 -
b0 G
b10 =
b0 7
1,
#1360
0,
#1370
b11 =
1,
#1380
0,
#1390
10
b0 1
b0 I
b100100100111 4
b10 !
b10 -
b10 G
b0 =
b101 2
b101 P
b100 (
b100 ?
b100 Q
b10 '
b10 A
1,
#1400
0,
#1410
b1 =
00
b1011 1
b1011 I
b111 "
b111 .
b111 H
b10 +
b10 8
b111 *
b111 9
1,
#1420
0,
#1430
x0
bx 1
bx I
bx !
bx -
bx G
b10 =
b10 7
1,
#1440
0,
#1450
b11 =
1,
#1460
0,
#1470
10
b0 1
b0 I
b10000100000 4
b111 !
b111 -
b111 G
b0 =
b110 2
b110 P
b101 (
b101 ?
b101 Q
b111 %
b111 C
1,
#1480
0,
#1490
b100100110000 4
1;
b1 3
b1 L
b0 <
b0 M
00
b111 1
b111 I
b0 "
b0 .
b0 H
b100 )
b100 >
b0 *
b0 9
1,
#1500
0,
#1510
b1 =
b1001 )
b1001 >
b11 +
b11 8
1,
#1520
0,
#1530
10
b0 1
b0 I
b0 !
b0 -
b0 G
b10 =
b11 7
1,
#1540
0,
#1550
b11 =
1,
#1560
0,
#1570
b111100000000 4
b0 =
b10 3
b10 L
b1 <
b1 M
1,
#1580
0,
#1590
b1 =
b1111 )
b1111 >
b0 +
b0 8
1,
#1600
0,
#1610
00
b10 1
b10 I
b10 !
b10 -
b10 G
b10 =
b0 7
1,
#1620
0,
#1630
10
b0 1
b0 I
b10 "
b10 .
b10 H
b11 =
0F
b10 6
b100 :
1,
#1640
0,
#1650
b1000000100 4
b0 =
b11 3
b11 L
b10 <
b10 M
1,
#1660
0,
#1670
b1 =
b10 )
b10 >
b100 *
b100 9
1,
#1680
0,
#1690
b10 =
1,
#1700
0,
#1710
b11 =
1,
#1720
0,
#1730
b101010110000 4
b0 =
b100 3
b100 L
b11 <
b11 M
1,
#1740
0,
#1750
b1 =
b1010 )
b1010 >
b10 #
b10 E
b11 +
b11 8
b0 *
b0 9
1,
#1760
0,
#1770
00
b111 1
b111 I
b0 !
b0 -
b0 G
b111 "
b111 .
b111 H
b10 =
15
b11 7
b10 :
1,
#1780
0,
#1790
b11 =
b111 6
b100 :
1,
#1800
0,
#1810
b1110 1
b1110 I
b110100000001 4
b111 !
b111 -
b111 G
b0 =
b101 3
b101 L
b100 <
b100 M
b111 $
b111 D
1,
#1820
0,
#1830
b1 =
b1101 )
b1101 >
b0 #
b0 E
b0 +
b0 8
b1 *
b1 9
1,
#1840
0,
#1850
b1 1
b1 I
b10 !
b10 -
b10 G
b1 "
b1 .
b1 H
b10 =
05
b0 7
b101 :
1,
#1860
0,
#1870
b11 =
b1 6
b100 :
1,
#1880
0,
#1890
10
b0 1
b0 I
b1100001110 4
b1 !
b1 -
b1 G
b0 =
b110 3
b110 L
b101 <
b101 M
b1 '
b1 A
1,
#1900
0,
#1910
b1 =
b11 )
b11 >
b1110 *
b1110 9
1,
#1920
0,
#1930
b10 =
1,
#1940
0,
#1950
b11 =
b11 3
b11 L
b11 2
b11 P
b1110 @
b1110 K
b1110 O
1,
#1960
0,
#1970
b101010110000 4
b0 =
b1 3
b1 L
b11 <
b11 M
1,
#1980
0,
#1990
b1 =
b1010 )
b1010 >
b10 #
b10 E
b11 +
b11 8
b0 *
b0 9
1,
#2000
0,
#2010
00
b1110 1
b1110 I
b111 !
b111 -
b111 G
b111 "
b111 .
b111 H
b10 =
15
b11 7
b10 :
1,
#2020
0,
#2030
b101 1
b101 I
b1110 "
b1110 .
b1110 H
b11 =
b1110 6
b100 :
b100 3
b100 L
b110 2
b110 P
b1 @
b1 K
b1 O
1,
#2040
0,
#2050
b1100 1
b1100 I
b110100000001 4
b1110 !
b1110 -
b1110 G
b0 =
b101 3
b101 L
b100 <
b100 M
b1110 $
b1110 D
1,
#2060
0,
#2070
b1 =
b1101 )
b1101 >
b0 #
b0 E
b0 +
b0 8
b1 *
b1 9
1,
#2080
0,
#2090
10
b0 1
b0 I
b1 !
b1 -
b1 G
b1 "
b1 .
b1 H
b10 =
05
b0 7
b101 :
1,
#2100
0,
#2110
00
b1 1
b1 I
b0 "
b0 .
b0 H
b11 =
1F
b0 6
b100 :
1,
#2120
0,
#2130
10
b0 1
b0 I
b1100001110 4
b0 !
b0 -
b0 G
b0 =
b110 3
b110 L
b101 <
b101 M
b0 '
b0 A
1,
#2140
0,
#2150
b1 =
b11 )
b11 >
b1110 *
b1110 9
1,
#2160
0,
#2170
b10 =
1,
#2180
0,
#2190
b11 =
1,
#2200
0,
#2210
b100011100000 4
b0 =
b111 3
b111 L
b110 <
b110 M
1,
#2220
0,
#2230
b1 =
b1000 )
b1000 >
b11 #
b11 E
b10 +
b10 8
b0 *
b0 9
1,
#2240
0,
#2250
00
b1001 1
b1001 I
b111 !
b111 -
b111 G
b1110 "
b1110 .
b1110 H
b10 =
b10 7
b11 :
1,
#2260
0,
#2270
b11 =
1,
#2280
0,
#2290
10
b0 1
b0 I
b100100110000 4
b1110 !
b1110 -
b1110 G
b0 =
b1000 3
b1000 L
b111 <
b111 M
b1110 %
b1110 C
1,
#2300
0,
#2310
b1 =
b1001 )
b1001 >
b0 #
b0 E
b11 +
b11 8
1,
#2320
0,
#2330
00
b1110 1
b1110 I
b0 "
b0 .
b0 H
b10 =
b11 7
b101 :
1,
#2340
0,
#2350
b11 =
1,
#2360
0,
#2370
10
b0 1
b0 I
b0 4
b0 !
b0 -
b0 G
b0 =
b1001 3
b1001 L
b1000 <
b1000 M
b0 $
b0 D
1,
#2380
0,
#2390
b111 2
b111 P
b110 (
b110 ?
b110 Q
0;
b0 )
b0 >
b0 +
b0 8
1,
#2400
0,
#2410
b1 =
1,
#2420
0,
#2430
b0 !
b0 -
b0 G
b10 =
b0 7
1,
#2440
0,
#2450
b11 =
b1000 3
b1000 L
b110 2
b110 P
b0 @
b0 K
b0 O
1,
#2460
0,
#2470
b0 =
1,
#2480
0,
#2490
b1 =
1,
#2500
0,
#2510
b10 =
1,
#2520
0,
#2530
b11 =
1,
#2540
0,
#2550
b0 =
1,
#2560
0,
#2570
b1 =
1,
#2580
0,
#2590
b10 =
1,
#2600
0,
#2610
b11 =
1,
#2620
0,
#2630
b0 =
1,
#2640
0,
#2650
b1 =
1,
#2660
0,
#2670
b10 =
1,
#2680
0,
#2690
b11 =
1,
#2700
0,
#2710
b0 =
1,
#2720
0,
#2730
b1 =
1,
#2740
0,
#2750
b10 =
1,
#2760
0,
#2770
b11 =
1,
#2780
0,
#2790
b0 =
1,
#2800
0,
#2810
b1 =
1,
#2820
0,
#2830
b10 =
1,
#2840
0,
#2850
b11 =
1,
#2860
0,
#2870
b0 =
1,
#2880
0,
#2890
b1 =
1,
#2900
0,
#2910
b10 =
1,
#2920
0,
#2930
b11 =
1,
#2940
0,
#2950
b0 =
1,
#2960
0,
#2970
b1 =
1,
#2980
0,
#2990
b10 =
1,
#3000
0,
#3010
b11 =
1,
#3020
0,
#3030
b0 =
1,
#3040
0,
#3050
b1 =
1,
#3060
0,
#3070
b10 =
1,
#3080
0,
#3090
b11 =
1,
#3100
0,
#3110
b0 =
1,
#3120
0,
#3130
b1 =
1,
#3140
0,
#3150
b10 =
1,
#3160
0,
#3170
b11 =
1,
#3180
0,
#3190
b0 =
1,
#3200
0,
#3210
b1 =
1,
#3220
0,
#3230
b10 =
1,
#3240
0,
#3250
b11 =
1,
#3260
0,
#3270
b0 =
1,
#3280
0,
#3290
b1 =
1,
#3300
0,
#3310
b10 =
1,
#3320
0,
#3330
b11 =
1,
#3340
0,
#3350
b0 =
1,
#3360
0,
#3370
b1 =
1,
#3380
0,
#3390
b10 =
1,
#3400
0,
#3410
b11 =
1,
#3420
0,
#3430
b0 =
1,
#3440
0,
#3450
b1 =
1,
#3460
0,
#3470
b10 =
1,
#3480
0,
#3490
b11 =
1,
#3500
0,
#3510
b0 =
1,
#3520
0,
#3530
b1 =
1,
#3540
0,
#3550
b10 =
1,
#3560
0,
#3570
b11 =
1,
#3580
0,
#3590
b0 =
1,
#3600
0,
#3610
b1 =
1,
#3620
0,
#3630
b10 =
1,
#3640
0,
#3650
b11 =
1,
#3660
0,
#3670
b0 =
1,
#3680
0,
#3690
b1 =
1,
#3700
0,
#3710
b10 =
1,
#3720
0,
#3730
b11 =
1,
#3740
0,
#3750
b0 =
1,
#3760
0,
#3770
b1 =
1,
#3780
0,
#3790
b10 =
1,
#3800
0,
#3810
b11 =
1,
#3820
0,
#3830
b0 =
1,
#3840
0,
#3850
b1 =
1,
#3860
0,
#3870
b10 =
1,
#3880
0,
#3890
b11 =
1,
#3900
0,
#3910
b0 =
1,
#3920
0,
#3930
b1 =
1,
#3940
0,
#3950
b10 =
1,
#3960
0,
#3970
b11 =
1,
#3980
0,
#3990
b0 =
1,
#4000
0,
#4010
b1 =
1,
#4020
0,
#4030
b10 =
1,
#4040
0,
#4050
b11 =
1,
#4060
0,
#4070
b0 =
1,
#4080
0,
#4090
b1 =
1,
#4100
0,
#4110
b10 =
1,
#4120
0,
#4130
b11 =
1,
#4140
0,
#4150
b0 =
1,
#4160
0,
#4170
b1 =
1,
#4180
0,
#4190
b10 =
1,
#4200
0,
#4210
b11 =
1,
#4220
0,
#4230
b0 =
1,
#4240
0,
#4250
b1 =
1,
#4260
0,
#4270
b10 =
1,
#4280
0,
#4290
b11 =
1,
#4300
0,
#4310
b0 =
1,
#4320
0,
#4330
b1 =
1,
#4340
0,
#4350
b10 =
1,
#4360
0,
#4370
b11 =
1,
#4380
0,
#4390
b0 =
1,
#4400
0,
#4410
b1 =
1,
#4420
0,
#4430
b10 =
1,
#4440
0,
#4450
b11 =
1,
#4460
0,
#4470
b0 =
1,
#4480
0,
#4490
b1 =
1,
#4500
0,
#4510
b10 =
1,
#4520
0,
#4530
b11 =
1,
#4540
0,
#4550
b0 =
1,
#4560
0,
#4570
b1 =
1,
#4580
0,
#4590
b10 =
1,
#4600
0,
#4610
b11 =
1,
#4620
0,
#4630
b0 =
1,
#4640
0,
#4650
b1 =
1,
#4660
0,
#4670
b10 =
1,
#4680
0,
#4690
b11 =
1,
#4700
0,
#4710
b0 =
1,
#4720
0,
#4730
b1 =
1,
#4740
0,
#4750
b10 =
1,
#4760
0,
#4770
b11 =
1,
#4780
0,
