CompArch/hw9/hw9/fa/mem_test_fa.v
/*          OPCODE SRC  DST  IMMDATA */
myROM[0]  = {movi, RXX, Rg0, 4'b1001};
myROM[1]  = {movi, RXX, Rg1, 4'b0101};
myROM[2]  = {sw,   Rg1, Rg0,  4'b0000}; // miss, it's a write

myROM[3]  = {lw,   Rg1, Rg0, 4'b0000}; // hit

myROM[4]  = {addi, RXX, Rg1, 4'b0010};
myROM[5]  = {lw,   Rg1, Rg2, 4'b0000}; //miss at address 7

myROM[6]  = {addi, RXX, Rg1, 4'b0010};
myROM[7]  = {lw,   Rg1, Rg2, 4'b0000}; //miss at address 9

myROM[8]  = {addi, RXX, Rg1, 4'b0010};
myROM[9]  = {lw,   Rg1, Rg2, 4'b0000}; //miss at address 11; cache is now full

myROM[10] = {movi, RXX, Rg1, 4'b0101};
myROM[11] = {lw,   Rg1, Rg2, 4'b0000}; // hit at addres 5: lru is now in address 7

myROM[12] = {movi, RXX, Rg1, 4'b1111};
myROM[13] = {lw,   Rg1, Rg2, 4'b0000}; // miss at address 15, line 1 (address 7) is evicted

myROM[14]  = {jmp,  RXX, RXX, 4'b0000}; // fini

/*
Miss! address:0101
Hit!  address:0101 value:1001
Miss! address:0111
Miss! address:1001
Miss! address:1011
Hit!  address:0101 value:1001
Miss! address:1111
Program halted normally after   168 cycles
Final state of register file:
    r0= 9
    r1=15
    r2=10
    r3= x
Final state of memory:
    0000    0100    1111    0011
    0001    1001    0110    1111
    0000    0000    0010    0110
    0100    1110    0000    1010
Final state of cache:
    Line:0  Valid:1  Tag:010  Timestamp:  135  Data:00011001
    Line:1  Valid:1  Tag:111  Timestamp:  165  Data:00001010
    Line:2  Valid:1  Tag:100  Timestamp:   96  Data:00000000
    Line:3  Valid:1  Tag:101  Timestamp:  126  Data:00100110

*/

CompArch/hw9/hw9/fa/E15Mem.v
module E15Mem(input clk, 
              input wire write_enable,
              input wire [3:0] address,
              input wire [3:0] valueIn,
              output reg [7:0] valueOut 
                  );
   reg [3:0] memory [15:0];
   
   always @(posedge clk)
   begin

      if (write_enable) 
        memory[address] = valueIn;
      valueOut <= #40 {memory[address & ~4'b0001], memory[address | 4'b0001]};
   end

endmodule

CompArch/hw9/hw9/fa/E15Cache_fa.v
`include "E15Mem.v"

// fully-associative cache
module E15Cache(input clk,
              input wire [15:0] cycleCount, // number of cycles elapsed so far
              input wire newRequest,        // true to signal a new memory request
              input wire write_enable,      // true if we are writing
              input wire [3:0] address,     // the address in question
              input wire [3:0] valueIn,     // the value to write
              output reg [3:0] valueOut,    // the value read
              output wire memResultReady    // true when it's safe to read valueOut
                  );

   /*
    This stores the content of the cache.
        Structure of a cache line:
          bit #    content
             27    valid
           26-24   tag
           23-8    timestamp
            7-0    data
     Initially, all cache lines are invalid
     (i.e. empty).
   */
   reg [27:0] cache [3:0];
   initial begin
        state = idle;
        cache[0][27] = 0;
        cache[1][27] = 0;
        cache[2][27] = 0;
        cache[3][27] = 0;
   end

   reg [3:0] saved_address;

   // If a read isn't in the cache, we have to consult main memory
   wire [7:0] main_memory_out;
   E15Mem main_memory(clk, write_enable, address, valueIn, main_memory_out);

   // If we have a cache miss, we need to stall until memory
   // is ready. The output memResultReady will tell the CPU
   // when it's safe to use valueOut.
   reg [7:0] stall;
   assign memResultReady = (state == ready);

   reg [1:0] state;
   parameter idle = 2'b0,
             stalling = 2'b1,
             access = 2'b10,
             ready = 2'b11;


   wire cacheHit;
   // TODO1: determine if the requested address is in the cache.
   // Write a Verilog expression on the right-hand side of the
   // equals sign that will evaluate to 1 if and only if
   // the requested address is in the cache.
   // Because this is a fully-associative cache, you'll have
   // to check each cache line, resulting in a long, kinda
   // repetitive expression. That's okay!
   // You'll need to use these values:
   //    cache: the cache memory itself
   //    address: the address that was requested by the program.
   //        This tells you which cache line to use.
   // For example:
   //     assign cacheHit = cache[address ...] || cache[address ...] || ... ;
   // assign cacheHit = 0;
   assign cacheHit = cache[0][26:24] == address[3:1] ||
                     cache[1][26:24] == address[3:1] ||
                     cache[2][26:24] == address[3:1] ||
                     cache[3][26:24] == address[3:1];

   wire [3:0] cachedValue;
   // TODO2: if the address is in the cache, get its value
   // Write a Verilog expression on the right-hand side of the
   // equals sign that will evaluate to the cached value at
   // the requested address. If the requested address is
   // not in the cache, the value of this wire is ignored.
   // Because this is a fully-associative cache, you'll have
   // to check each cache line, resulting in a long, kinda
   // repetitive expression. That's okay!
   // You'll need to use these values:
   //    cache: the cache memory itself
   //    address: the address that was requested by the program.
   //        This tells you which cache line to use.
   // Note that cachedValue is a 4-bit value, even though
   // each block is 8 bits. You'll need to decide which half
   // of the block to return.
   // For example:
   //     assign cacheValue = cache[address ...] == ... ? cache[address ...] :
   //                         cache[address ...] == ... ? cache[address ...] : ...;
   assign cachedValue = cache[0][26:24] == address[3:1] ? address[0] ? cache[0][3:0] : cache[0][7:4] :
                        cache[1][26:24] == address[3:1] ? address[0] ? cache[1][3:0] : cache[1][7:4] :
                        cache[2][26:24] == address[3:1] ? address[0] ? cache[2][3:0] : cache[2][7:4] :
                        cache[3][26:24] == address[3:1] ? address[0] ? cache[3][3:0] : cache[3][7:4] : 0;


   always @(posedge clk)
   case (state)
        idle:
            if (newRequest) begin
                saved_address <= address;
                if (~write_enable && cacheHit)
                begin
                    // we have the value in cache, return it ASAP
                    $display("Hit!  address:%b value:%b",address,cachedValue);
                    valueOut <= cachedValue;
                    // TODO4: Update timestamp on a hit
                    // This code is executed when a cache hit occurs, which means
                    // we need to update the timestamp on the cacheline that
                    // was just used. This ensures that the least-recently
                    // used line will be evicted when a miss happens.
                    // Use the values cache, address, and cycleCount.
                    // You don't need to modify any of the code here, just
                    // add code that will update the timestamp for
                    // For example:
                    //    if (cache[....]==address[....])
                    //       cache[...] <= cycleCount;
                    //    else if (cahce[....]==address[....])
                    //       cache[...] <= cycleCount;
                    //    else ...
                    // YOUR CODE HERE
                    if (cache[0][26:24] == address[3:1])
                      cache[0][23:8] <= cycleCount;
                    else if (cache[1][26:24] == address[3:1])
                      cache[1][23:8] <= cycleCount;
                    else if (cache[2][26:24] == address[3:1])
                       cache[2][23:8] <= cycleCount;
                    else cache[3][23:8] <= cycleCount;
                    state <= ready;
                end
                else begin
                    // all writes have to go to main memory, so we treat them as misses
                    $display("Miss! address:%b", address);
                    stall <= 19;
                    state <= stalling;
                end
            end
        stalling:
            // wait for main memory to complete
            if (stall == 0)
                state <= access;
            else
                stall <= stall - 1;
        access:
            // memory access is done: get the value, return it, and cache the result
            begin
                // TODO3: save value into a cache line
                // In the event of a cache miss, this code will store the value
                // returned from main memory into the appropriate cache line.
                // Since this is a fully-associative cache, we should prefer
                // to store the value into an empty cache line (i.e. a cache line
                // whose valid bit is 0). If there is no empty cache line, then
                // we have to evict the cache line that was least recently used,
                // (i.e. the one with the lowest timestamp), so you'll need to
                // compare, sequentially, the timestamp of each of the four
                // cache lines with that of the others, until we can find the
                // lowest. Your code doesn't need to be pretty, repetitive
                // is fine.
                // You'll need to use these values:
                //   cache: the cache itself
                //   saved_address: the address that was requested. This will
                //      tell you which cache line to use.
                //   main_memory_out: this is the 8-bit block returned by
                //      the main memory unit.
                //   cycleCount: the number of cycles elapsed in the CPU
                //      since it was turned on. Use this as the timestamp
                //      in the cacheline.
                // For example:
                //   if (cache...)
                //     cache[...] <= ...;
                //   else if (cache....)
                //     cache[....] <= ...;
                // You are given code that will send the value from main memory
                // back to the CPU. You don't need to change that, only to add
                // code that will update the cache.
                // YOUR CODE HERE
                valueOut <= (saved_address[0])?main_memory_out[3:0]:main_memory_out[7:4];
                if (cache[0][27] == 0)
                  begin
                    cache[0][27] <= 1;
  		   			      cache[0][26:24] <= saved_address[3:1];
  		   			      cache[0][23:8] <= cycleCount;
                    cache[0][7:0] <= main_memory_out;
		   		        end
				        else if (cache[1][27] == 0)
                  begin
                    cache[1][27] <= 1;
                    cache[1][26:24] <= saved_address[3:1];
                    cache[1][23:8] <= cycleCount;
                    cache[1][7:0] <= main_memory_out;
				          end
				        else if (cache[2][27] == 0)
                  begin
                    cache[2][27] <= 1;
                    cache[2][26:24] <= saved_address[3:1];
                    cache[2][23:8] <= cycleCount;
                    cache[2][7:0] <= main_memory_out;
				          end
        				else if (cache[3][27]==0)
                  begin
                    cache[3][27] <= 1;
                    cache[3][26:24] <= saved_address[3:1];
                    cache[3][23:8] <= cycleCount;
                    cache[3][7:0] <= main_memory_out;
        				  end
        				else
                  begin
          					if (cache[0][23:8] < cache[1][23:8] &&
                        cache[0][23:8] < cache[2][23:8] &&
          						  cache[0][23:8] < cache[3][23:8])
                      begin
          							cache[0][26:24] <= saved_address[3:1];
          							cache[0][23:8] <= cycleCount;
                        cache[0][7:0] <= main_memory_out;
          				    end
          					else if (cache[1][23:8] < cache[0][23:8] &&
          						       cache[1][23:8] < cache[2][23:8] &&
          						       cache[1][23:8] < cache[3][23:8])
                      begin
          							cache[1][26:24] <= saved_address[3:1];
          							cache[1][23:8] <= cycleCount;
                        cache[1][7:0] <= main_memory_out;
          						end
          					else if (cache[2][23:8] < cache[0][23:8] &&
          						       cache[2][23:8] < cache[1][23:8] &&
          						       cache[2][23:8] < cache[3][23:8])
                      begin
          							cache[2][26:24] <= saved_address[3:1];
          							cache[2][23:8] <= cycleCount;
                        cache[2][7:0] <= main_memory_out;
          						end
          					else
                      begin
          						  cache[3][26:24] <= saved_address[3:1];
          						  cache[3][23:8] <= cycleCount;
                        cache[3][7:0] <= main_memory_out;
          					  end
        				  end
                state <= ready;
            end
        ready:
            // wait for CPU to read the result and then start waiting again
            begin
                state <= idle;
            end
   endcase

endmodule

CompArch/hw9/hw9/fa/E15Process_memc_fa.v
`include "E15Cache_fa.v"

module E15Process(input clk, 
                  output reg [3:0] pc,             // Program Counter
                  output reg [3:0] opCode,         // op code
                  output reg [1:0] src, dst,       // src and dst register
                  output reg [3:0] immData,        // "Immediate" data
                  output reg [3:0] r0, r1, r2, r3, // Registers
                  output tri [3:0] mBus, dstBus    // Buses
                  );

   parameter fetch=2'd0, decode=2'd1, exec=2'd2, store=2'd3;

   parameter Rg0 = 2'b00, Rg1 = 2'b01, Rg2 = 2'b10, Rg3 = 2'b11, 
             RXX = 2'b00;

   parameter
     jmp  = 4'b0000, jz   = 4'b0010,  jnz = 4'b0011,
     movi = 4'b1001, mov  = 4'b1000,
     addi = 4'b1011, add  = 4'b1010,
     subi = 4'b1101, sub  = 4'b1100,
     cmpi = 4'b1111, cmp  = 4'b1110,
     lw = 4'b0100, sw = 4'b0101;
   
   parameter   hiZ = 4'bz;

   parameter   bEn_R0 = 3'd0, bEn_R1 = 3'd1, 
     bEn_R2 = 3'd2, bEn_R3 = 3'd3, 
     bEn_ALU = 3'd4, bEn_Imm = 3'd5;

   reg  [3:0] pcIncr; // Program Counter Increment
   wire [3:0] pcRes;  // Output of pc ALU
   wire       pcz;    // Unused - zero flag for pc ALU
   
   reg [1:0]  myState;      // State (phase of excution)
   reg [11:0] myROM [15:0]; // ROM (holds program)
   reg [3:0]  mbEn, dbEn;   // Used to determine which tri-state buffers are 
                            // enabled for master bus and destination bus.

   reg       mmuControlToggle; // are we initiating a new memory request
   reg       mmuControl; // read or write the mmu
   wire [3:0] mmuValueOut; // output value from mmu
   reg        addNotSub; // Determines if ALU adds or subtracts
   reg [3:0]  aluOut;    // Register to hold output of main ALU
   reg        zFlag;     // Zero flag
   wire [3:0] resVal;    // Output (combinational) of ALU
   wire       zVal;      // Output (combinational) of ALU zero flag

   reg [15:0] cycleCount = 16'd0; // count the numer of cycles we're running for
   wire       memResultReady;     // output from the cache unit if we got a hit

   initial
     begin

        `include "mem_test_fa.v"
        
        pc = 4'b0000;
        myState = fetch;
        
     end
   
   always @(posedge clk)
     begin
     case(myState)
       fetch:
         begin
            {opCode, src, dst, immData} = myROM[pc];
            mmuControl <= 0; mmuControlToggle <= 0;
            myState <= decode;

            // count the number of cycles the program runs, for timing the cache
            if (myROM[pc] == {jmp, RXX, RXX, 4'b0000}) begin
                myROM[pc] <= {jmp, RXX, Rg1, 4'b0000};
                $display("Program halted normally after %d cycles", cycleCount);
            end

         end

       decode:
         begin
            case(opCode)
              movi, addi, subi, cmpi:
                begin
                   mbEn <= bEn_Imm;
                end
              mov, add, sub, cmp, lw, sw:
                case(src)
                  Rg0: mbEn <= bEn_R0;
                  Rg1: mbEn <= bEn_R1;
                  Rg2: mbEn <= bEn_R2;
                  Rg3: mbEn <= bEn_R3;
                endcase
            endcase 
            
            case(dst)
              Rg0: dbEn <= bEn_R0;
              Rg1: dbEn <= bEn_R1;
              Rg2: dbEn <= bEn_R2;
              Rg3: dbEn <= bEn_R3;
            endcase

            mmuControl <= opCode == sw;
            mmuControlToggle <= (opCode == sw) | (opCode == lw); 
            addNotSub <= ((opCode == add) | (opCode == addi));
            myState <= exec;

         end
       
       exec:
         if ((opCode == lw || opCode == sw) && ~memResultReady)
            mmuControlToggle <= 1'b0;
         else 
         begin
            mmuControlToggle <= 1'b0;
            case(opCode)
              lw:
                begin
                   pcIncr <= 4'd1;
                   mbEn <= bEn_ALU;
                   aluOut <= mmuValueOut;
                end
              addi, add, subi, sub, cmpi, cmp:
                begin
                   pcIncr <= 4'd1;
                   mbEn <= bEn_ALU;
                   aluOut <= resVal;
                   zFlag <= zVal;
                end
              jmp: pcIncr <= immData;
              jz:  pcIncr <= zFlag ? immData : 4'd1;
              jnz: pcIncr <= zFlag ? 4'd1 : immData;
              default: pcIncr <= 4'd1; 
            endcase
            myState <= store;
         end
       
       store:
         begin
            case(opCode)
              movi, mov, add, addi, sub, subi, lw:
                case(dst)
                  Rg0: r0 <= mBus;
                  Rg1: r1 <= mBus;
                  Rg2: r2 <= mBus;
                  Rg3: r3 <= mBus;
                endcase
            endcase
            pc <= pcRes;
            mmuControl <= 0;
            myState <= fetch;
         end
       
     endcase
     cycleCount <= cycleCount + 1;
   end

   assign mBus = (mbEn==bEn_R0)  ? r0      : hiZ;
   assign mBus = (mbEn==bEn_R1)  ? r1      : hiZ;
   assign mBus = (mbEn==bEn_R2)  ? r2      : hiZ;
   assign mBus = (mbEn==bEn_R3)  ? r3      : hiZ;
   assign mBus = (mbEn==bEn_Imm) ? immData : hiZ;
   assign mBus = (mbEn==bEn_ALU) ? aluOut  : hiZ;

   assign dstBus = (dbEn==bEn_R0)  ? r0 : hiZ;
   assign dstBus = (dbEn==bEn_R1)  ? r1 : hiZ;
   assign dstBus = (dbEn==bEn_R2)  ? r2 : hiZ;
   assign dstBus = (dbEn==bEn_R3)  ? r3 : hiZ;

   simpleALU dataALU(addNotSub, mBus, dstBus, zVal, resVal);
   simpleALU pcALU(1'b1, pc, pcIncr, pcz, pcRes);

   E15Cache CachedMMU(clk, cycleCount, mmuControlToggle, mmuControl, mBus, dstBus, mmuValueOut, memResultReady);

endmodule


module simpleALU(
    input addNotSub,
    input [3:0] src, dst,
    output zFlag,
    output [3:0] res);
    assign res = addNotSub ? dst + src : dst - src;
    assign zFlag = !(res);

endmodule

CompArch/hw9/hw9/fa/E15Process_memc_fa_tb.v
`default_nettype none
`timescale 1ns/100ps
`include "E15Process_memc_fa.v"

module E15Process_TB;

   reg clk = 0;

   wire [3:0] pc;
   wire [3:0] opCode;
   wire [1:0] src, dst;
   wire [3:0] immData;
   wire [3:0] r0, r1, r2, r3;
   tri [3:0]  mBus, dstBus;

   E15Process proc(clk, pc, opCode, src, dst, immData, 
                   r0, r1, r2, r3, mBus, dstBus);

   always #1
     clk = ~clk;

   integer i;
   initial begin
      proc.CachedMMU.main_memory.memory[0] = 0;
      proc.CachedMMU.main_memory.memory[1] = 4;
      proc.CachedMMU.main_memory.memory[2] = 15;
      proc.CachedMMU.main_memory.memory[3] = 3;
      proc.CachedMMU.main_memory.memory[4] = 1;
      proc.CachedMMU.main_memory.memory[5] = 14;
      proc.CachedMMU.main_memory.memory[6] = 6;
      proc.CachedMMU.main_memory.memory[7] = 15;
      proc.CachedMMU.main_memory.memory[8] = 0;
      proc.CachedMMU.main_memory.memory[9] = 0;
      proc.CachedMMU.main_memory.memory[10] = 2;
      proc.CachedMMU.main_memory.memory[11] = 6;
      proc.CachedMMU.main_memory.memory[12] = 4;
      proc.CachedMMU.main_memory.memory[13] = 14;
      proc.CachedMMU.main_memory.memory[14] = 0;
      proc.CachedMMU.main_memory.memory[15] = 10;

      $dumpfile("E15Process_memc_tb.vcd");
      $dumpvars(0, E15Process_TB);
      #1000

      $display("Final state of register file:\n\tr0=%d\n\tr1=%d\n\tr2=%d\n\tr3=%d", r0, r1, r2, r3);

      $write("Final state of memory:");
      for (i=0; i< 16; i=i+1) begin
        if (i % 4 == 0) begin
          $write("\n");
        end
        $write("\t%b", proc.CachedMMU.main_memory.memory[i]);
      end
      $write("\n");

      $write("Final state of cache:\n");
      for (i=0; i< 4; i=i+1) begin
        $write("\tLine:%1d  Valid:%b  Tag:%b  Timestamp:%5d  Data:%b\n",i,
            proc.CachedMMU.cache[i][27],
            proc.CachedMMU.cache[i][26:24],
            proc.CachedMMU.cache[i][23:8],
            proc.CachedMMU.cache[i][7:0]
            );
      end

      $finish;
   end

endmodule // E15ProcessTB

CompArch/hw9/hw9/fa/E15Process_memc_tb.vcd
$date
	Fri May 10 20:08:11 2019
$end
$version
	Icarus Verilog
$end
$timescale
	100ps
$end
$scope module E15Process_TB $end
$var wire 4 ! dstBus [3:0] $end
$var wire 4 " mBus [3:0] $end
$var wire 2 # src [1:0] $end
$var wire 4 $ r3 [3:0] $end
$var wire 4 % r2 [3:0] $end
$var wire 4 & r1 [3:0] $end
$var wire 4 ' r0 [3:0] $end
$var wire 4 ( pc [3:0] $end
$var wire 4 ) opCode [3:0] $end
$var wire 4 * immData [3:0] $end
$var wire 2 + dst [1:0] $end
$var reg 1 , clk $end
$var integer 32 - i [31:0] $end
$scope module proc $end
$var wire 1 , clk $end
$var wire 4 . dstBus [3:0] $end
$var wire 4 / mBus [3:0] $end
$var wire 1 0 zVal $end
$var wire 4 1 resVal [3:0] $end
$var wire 1 2 pcz $end
$var wire 4 3 pcRes [3:0] $end
$var wire 4 4 mmuValueOut [3:0] $end
$var wire 1 5 memResultReady $end
$var reg 1 6 addNotSub $end
$var reg 4 7 aluOut [3:0] $end
$var reg 16 8 cycleCount [15:0] $end
$var reg 4 9 dbEn [3:0] $end
$var reg 2 : dst [1:0] $end
$var reg 4 ; immData [3:0] $end
$var reg 4 < mbEn [3:0] $end
$var reg 1 = mmuControl $end
$var reg 1 > mmuControlToggle $end
$var reg 2 ? myState [1:0] $end
$var reg 4 @ opCode [3:0] $end
$var reg 4 A pc [3:0] $end
$var reg 4 B pcIncr [3:0] $end
$var reg 4 C r0 [3:0] $end
$var reg 4 D r1 [3:0] $end
$var reg 4 E r2 [3:0] $end
$var reg 4 F r3 [3:0] $end
$var reg 2 G src [1:0] $end
$var reg 1 H zFlag $end
$scope module CachedMMU $end
$var wire 4 I address [3:0] $end
$var wire 1 J cacheHit $end
$var wire 1 , clk $end
$var wire 16 K cycleCount [15:0] $end
$var wire 1 > newRequest $end
$var wire 4 L valueIn [3:0] $end
$var wire 1 = write_enable $end
$var wire 1 5 memResultReady $end
$var wire 8 M main_memory_out [7:0] $end
$var wire 4 N cachedValue [3:0] $end
$var reg 4 O saved_address [3:0] $end
$var reg 8 P stall [7:0] $end
$var reg 2 Q state [1:0] $end
$var reg 4 R valueOut [3:0] $end
$scope module main_memory $end
$var wire 4 S address [3:0] $end
$var wire 1 , clk $end
$var wire 4 T valueIn [3:0] $end
$var wire 1 = write_enable $end
$var reg 8 U valueOut [7:0] $end
$upscope $end
$upscope $end
$scope module dataALU $end
$var wire 1 6 addNotSub $end
$var wire 4 V dst [3:0] $end
$var wire 4 W src [3:0] $end
$var wire 1 0 zFlag $end
$var wire 4 X res [3:0] $end
$upscope $end
$scope module pcALU $end
$var wire 1 Y addNotSub $end
$var wire 4 Z dst [3:0] $end
$var wire 4 [ res [3:0] $end
$var wire 4 \ src [3:0] $end
$var wire 1 2 zFlag $end
$upscope $end
$upscope $end
$upscope $end
$enddefinitions $end
#0
$dumpvars
b0 \
bx [
bx Z
1Y
bx X
bx W
bx V
bx U
bx T
bx S
bx R
b0 Q
bx P
bx O
bx N
bx M
bx L
b0 K
xJ
bx I
xH
bx G
bx F
bx E
bx D
bx C
bx B
b0 A
bx @
b0 ?
x>
x=
bx <
bx ;
bx :
bx 9
b0 8
bx 7
x6
05
bx 4
bx 3
x2
bx 1
x0
bx /
bx .
bx -
0,
bx +
bx *
bx )
b0 (
bx '
bx &
bx %
bx $
bx #
bx "
bx !
$end
#10
b1 8
b1 K
b1 ?
0>
0=
b1001 )
b1001 @
b0 #
b0 G
b0 +
b0 :
b1001 *
b1001 ;
1,
#20
0,
#30
b1001 "
b1001 /
b1001 I
b1001 S
b1001 W
b10 8
b10 K
b10 ?
06
b0 9
b101 <
1,
#40
0,
#50
b11 8
b11 K
b11 ?
02
b1 3
b1 [
b1 B
b1 Z
1,
#60
0,
#70
10
b0 1
b0 X
b1001 !
b1001 .
b1001 L
b1001 T
b1001 V
b100 8
b100 K
b0 ?
b10 3
b10 [
b1 (
b1 A
b1 \
b1001 '
b1001 C
1,
#80
0,
#90
b101 8
b101 K
b1 ?
00
b100 1
b100 X
b101 "
b101 /
b101 I
b101 S
b101 W
b1 +
b1 :
b101 *
b101 ;
1,
#100
0,
#110
x0
bx 1
bx X
bx !
bx .
bx L
bx T
bx V
b110 8
b110 K
b10 ?
b1 9
1,
#120
0,
#130
b111 8
b111 K
b11 ?
1,
#140
0,
#150
10
b0 1
b0 X
b101 !
b101 .
b101 L
b101 T
b101 V
b1000 8
b1000 K
b0 ?
b11 3
b11 [
b10 (
b10 A
b10 \
b101 &
b101 D
1,
#160
0,
#170
b1001 8
b1001 K
b1 ?
00
b101 1
b101 X
b0 "
b0 /
b0 I
b0 S
b0 W
b101 )
b101 @
b1 #
b1 G
b0 +
b0 :
b0 *
b0 ;
1,
#180
0,
#190
b100 1
b100 X
b1001 !
b1001 .
b1001 L
b1001 T
b1001 V
b101 "
b101 /
b101 I
b101 S
b101 W
b1010 8
b1010 K
b10 ?
1>
1=
b0 9
b1 <
1,
#200
0,
#210
b1 Q
b10011 P
b101 O
b1011 8
b1011 K
0>
1,
#220
0,
#230
b1100 8
b1100 K
b10010 P
1,
#240
0,
#250
b10001 P
b1101 8
b1101 K
1,
#260
0,
#270
b1110 8
b1110 K
b10000 P
1,
#280
0,
#290
b1111 P
b1111 8
b1111 K
1,
#300
0,
#310
b10000 8
b10000 K
b1110 P
1,
#320
0,
#330
b1101 P
b10001 8
b10001 K
1,
#340
0,
#350
b10010 8
b10010 K
b1100 P
1,
#360
0,
#370
b1011 P
b10011 8
b10011 K
1,
#380
0,
#390
b10100 8
b10100 K
b1010 P
1,
#400
0,
#410
b1001 P
b10101 8
b10101 K
1,
#420
0,
#430
b10110 8
b10110 K
b1000 P
1,
#440
0,
#450
b111 P
b10111 8
b10111 K
b0 M
b0 U
1,
#460
0,
#470
b11000 8
b11000 K
b110 P
1,
#480
0,
#490
b101 P
b11001 8
b11001 K
1,
#500
0,
#510
b11010 8
b11010 K
b100 P
b11110 M
b11110 U
1,
#520
0,
#530
b11 P
b11011 8
b11011 K
1,
#540
0,
#550
b11100 8
b11100 K
b10 P
1,
#560
0,
#570
b1 P
b11101 8
b11101 K
1,
#580
0,
#590
b11110 8
b11110 K
b0 P
b100 M
b100 U
1,
#600
0,
#610
b10 Q
b11111 8
b11111 K
b11001 M
b11001 U
1,
#620
0,
#630
1J
b1001 N
b100000 8
b100000 K
15
b11 Q
b1001 4
b1001 R
1,
#640
0,
#650
05
b0 Q
b100001 8
b100001 K
b11 ?
1,
#660
0,
#670
b100010 8
b100010 K
b0 ?
0=
b100 3
b100 [
b11 (
b11 A
b11 \
1,
#680
0,
#690
b100011 8
b100011 K
b1 ?
b100 )
b100 @
1,
#700
0,
#710
b100100 8
b100100 K
b10 ?
1>
1,
#720
0,
#730
15
b11 Q
b100101 8
b100101 K
0>
1,
#740
0,
#750
xJ
bx N
10
b0 1
b0 X
b1001 "
b1001 /
b1001 I
b1001 S
b1001 W
b100110 8
b100110 K
b11 ?
b1001 7
b100 <
05
b0 Q
1,
#760
0,
#770
b100111 8
b100111 K
b0 ?
b101 3
b101 [
b100 (
b100 A
b100 \
1,
#780
0,
#790
b101000 8
b101000 K
b1 ?
b1011 )
b1011 @
b0 #
b0 G
b1 +
b1 :
b10 *
b10 ;
1,
#800
0,
#810
00
b111 1
b111 X
b101 !
b101 .
b101 L
b101 T
b101 V
b10 "
b10 /
b10 I
b10 S
b10 W
b101001 8
b101001 K
b10 ?
16
b1 9
b101 <
1,
#820
0,
#830
b1100 1
b1100 X
b111 "
b111 /
b111 I
b111 S
b111 W
b101010 8
b101010 K
b11 ?
0H
b111 7
b100 <
1,
#840
0,
#850
b1110 1
b1110 X
b111 !
b111 .
b111 L
b111 T
b111 V
b101011 8
b101011 K
b0 ?
b110 3
b110 [
b101 (
b101 A
b101 \
b111 &
b111 D
1,
#860
0,
#870
b101100 8
b101100 K
b1 ?
b100 )
b100 @
b1 #
b1 G
b10 +
b10 :
b0 *
b0 ;
1,
#880
0,
#890
x0
bx 1
bx X
bx !
bx .
bx L
bx T
bx V
b111 "
b111 /
b111 I
b111 S
b111 W
b101101 8
b101101 K
b10 ?
06
1>
b10 9
b1 <
1,
#900
0,
#910
b101110 8
b101110 K
0>
b1 Q
b10011 P
b111 O
1,
#920
0,
#930
b10010 P
b101111 8
b101111 K
1,
#940
0,
#950
b110000 8
b110000 K
b10001 P
1,
#960
0,
#970
b10000 P
b110001 8
b110001 K
1,
#980
0,
#990
b110010 8
b110010 K
b1111 P
1,
#1000
0,
#1010
b1110 P
b110011 8
b110011 K
1,
#1020
0,
#1030
b110100 8
b110100 K
b1101 P
1,
#1040
0,
#1050
b1100 P
b110101 8
b110101 K
1,
#1060
0,
#1070
b110110 8
b110110 K
b1011 P
1,
#1080
0,
#1090
b1010 P
b110111 8
b110111 K
1,
#1100
0,
#1110
b111000 8
b111000 K
b1001 P
1,
#1120
0,
#1130
b1000 P
b111001 8
b111001 K
1,
#1140
0,
#1150
b111010 8
b111010 K
b111 P
1,
#1160
0,
#1170
b110 P
b111011 8
b111011 K
b0 M
b0 U
1,
#1180
0,
#1190
b111100 8
b111100 K
b101 P
1,
#1200
0,
#1210
b100 P
b111101 8
b111101 K
1,
#1220
0,
#1230
b111110 8
b111110 K
b11 P
b11110011 M
b11110011 U
1,
#1240
0,
#1250
b10 P
b111111 8
b111111 K
b1101111 M
b1101111 U
1,
#1260
0,
#1270
b1000000 8
b1000000 K
b1 P
1,
#1280
0,
#1290
b0 P
b1000001 8
b1000001 K
1,
#1300
0,
#1310
b1000010 8
b1000010 K
b10 Q
1,
#1320
0,
#1330
b1111 N
1J
15
b11 Q
b1111 4
b1111 R
b1000011 8
b1000011 K
1,
#1340
0,
#1350
xJ
bx N
b1111 "
b1111 /
b1111 I
b1111 S
b1111 W
b1000100 8
b1000100 K
b11 ?
b1111 7
b100 <
05
b0 Q
1,
#1360
0,
#1370
10
b0 1
b0 X
b1111 !
b1111 .
b1111 L
b1111 T
b1111 V
b1000101 8
b1000101 K
b0 ?
b111 3
b111 [
b110 (
b110 A
b110 \
b1111 %
b1111 E
1,
#1380
0,
#1390
b1000110 8
b1000110 K
b1 ?
b1011 )
b1011 @
b0 #
b0 G
b1 +
b1 :
b10 *
b10 ;
1,
#1400
0,
#1410
00
b1001 1
b1001 X
b111 !
b111 .
b111 L
b111 T
b111 V
b10 "
b10 /
b10 I
b10 S
b10 W
b1000111 8
b1000111 K
b10 ?
16
b1 9
b101 <
1,
#1420
0,
#1430
10
b0 1
b0 X
b1001 "
b1001 /
b1001 I
b1001 S
b1001 W
b1001000 8
b1001000 K
b11 ?
b1001 7
b100 <
1,
#1440
0,
#1450
00
b10 1
b10 X
b1001 !
b1001 .
b1001 L
b1001 T
b1001 V
b1001001 8
b1001001 K
b0 ?
b1000 3
b1000 [
b111 (
b111 A
b111 \
b1001 &
b1001 D
1,
#1460
0,
#1470
b1001010 8
b1001010 K
b1 ?
b100 )
b100 @
b1 #
b1 G
b10 +
b10 :
b0 *
b0 ;
1,
#1480
0,
#1490
b110 1
b110 X
b1111 !
b1111 .
b1111 L
b1111 T
b1111 V
b1001 "
b1001 /
b1001 I
b1001 S
b1001 W
b1001011 8
b1001011 K
b10 ?
06
1>
b10 9
b1 <
1,
#1500
0,
#1510
b1001100 8
b1001100 K
0>
b1 Q
b10011 P
b1001 O
1,
#1520
0,
#1530
b10010 P
b1001101 8
b1001101 K
1,
#1540
0,
#1550
b1001110 8
b1001110 K
b10001 P
1,
#1560
0,
#1570
b10000 P
b1001111 8
b1001111 K
1,
#1580
0,
#1590
b1010000 8
b1010000 K
b1111 P
1,
#1600
0,
#1610
b1110 P
b1010001 8
b1010001 K
1,
#1620
0,
#1630
b1010010 8
b1010010 K
b1101 P
1,
#1640
0,
#1650
b1100 P
b1010011 8
b1010011 K
1,
#1660
0,
#1670
b1010100 8
b1010100 K
b1011 P
1,
#1680
0,
#1690
b1010 P
b1010101 8
b1010101 K
1,
#1700
0,
#1710
b1010110 8
b1010110 K
b1001 P
1,
#1720
0,
#1730
b1000 P
b1010111 8
b1010111 K
1,
#1740
0,
#1750
b1011000 8
b1011000 K
b111 P
1,
#1760
0,
#1770
b110 P
b1011001 8
b1011001 K
b1010 M
b1010 U
1,
#1780
0,
#1790
b1011010 8
b1011010 K
b101 P
1,
#1800
0,
#1810
b100 P
b1011011 8
b1011011 K
1,
#1820
0,
#1830
b1011100 8
b1011100 K
b11 P
b11110011 M
b11110011 U
1,
#1840
0,
